<?xml version="1.0" encoding="UTF-8"?>

<entity-facade-xml type="seed">
    <moqui.basic.LocalizedEntityField entityName="moqui.basic.Geo" fieldName="geoName" pkValue="CHN" locale="zh_CN" localized="中国"/>
    <moqui.basic.LocalizedEntityField entityName="moqui.basic.Geo" fieldName="geoName" pkValue="DEU" locale="zh_CN" localized="德国"/>
    <moqui.basic.LocalizedEntityField entityName="moqui.basic.Geo" fieldName="geoName" pkValue="JPN" locale="zh_CN" localized="日本"/>
    <moqui.basic.LocalizedEntityField entityName="moqui.basic.StatusItem" fieldName="description" pkValue="OrderSent" locale="zh_CN" localized="已发送"/>
    <moqui.basic.LocalizedEntityField entityName="moqui.basic.StatusItem" fieldName="description" pkValue="OrderCompleted" locale="zh_CN" localized="已完成"/>

    <moqui.screen.SubscreensItem screenLocation="component://webroot/screen/webroot/apps.xml"
                             subscreenName="km" menuTitle="Kissimee Commerce" menuIndex="1" menuInclude="Y"
                             subscreenLocation="component://kissimee/screen/KMApp.xml"/>

    <moqui.security.UserGroup userGroupId="KMAPP_ADMIN" description="KM App Administrators"/>

    <!-- KM App root screen -->
    <moqui.security.ArtifactGroup artifactGroupId="KM_APP" description="Kissimee app"/>

    <moqui.security.ArtifactGroupMember artifactGroupId="KM_APP" artifactName="component://kissimee/screen/KMApp.xml"
                                        artifactTypeEnumId="AT_XML_SCREEN" inheritAuthz="Y"/>

    <moqui.security.ArtifactAuthz artifactAuthzId="KM_APP_ADMIN" userGroupId="KMAPP_ADMIN" artifactGroupId="KM_APP"
                                  authzTypeEnumId="AUTHZT_ALWAYS" authzActionEnumId="AUTHZA_ALL"/>

    <moqui.security.UserGroupMember userGroupId="KMAPP_ADMIN" userId="EX_JOHN_DOE" fromDate="1265184000000"/>

    <moqui.basic.Geo geoId="CHN_11_1" geoTypeEnumId="GEOT_CITY" geoNameLocal="东城区"/>
    <moqui.basic.Geo geoId="CHN_11_2" geoTypeEnumId="GEOT_CITY" geoNameLocal="西城区"/>
    <moqui.basic.Geo geoId="CHN_11_3" geoTypeEnumId="GEOT_CITY" geoNameLocal="崇文区"/>
    <moqui.basic.Geo geoId="CHN_11_4" geoTypeEnumId="GEOT_CITY" geoNameLocal="宣武区"/>
    <moqui.basic.Geo geoId="CHN_11_5" geoTypeEnumId="GEOT_CITY" geoNameLocal="朝阳区"/>
    <moqui.basic.Geo geoId="CHN_11_6" geoTypeEnumId="GEOT_CITY" geoNameLocal="丰台区"/>
    <moqui.basic.Geo geoId="CHN_11_7" geoTypeEnumId="GEOT_CITY" geoNameLocal="石景山区"/>
    <moqui.basic.Geo geoId="CHN_11_8" geoTypeEnumId="GEOT_CITY" geoNameLocal="海淀区"/>
    <moqui.basic.Geo geoId="CHN_11_9" geoTypeEnumId="GEOT_CITY" geoNameLocal="门头沟区"/>
    <moqui.basic.Geo geoId="CHN_11_10" geoTypeEnumId="GEOT_CITY" geoNameLocal="房山区"/>
    <moqui.basic.Geo geoId="CHN_11_11" geoTypeEnumId="GEOT_CITY" geoNameLocal="通州区"/>
    <moqui.basic.Geo geoId="CHN_11_12" geoTypeEnumId="GEOT_CITY" geoNameLocal="顺义区"/>
    <moqui.basic.Geo geoId="CHN_11_13" geoTypeEnumId="GEOT_CITY" geoNameLocal="昌平区"/>
    <moqui.basic.Geo geoId="CHN_11_14" geoTypeEnumId="GEOT_CITY" geoNameLocal="大兴区"/>
    <moqui.basic.Geo geoId="CHN_11_15" geoTypeEnumId="GEOT_CITY" geoNameLocal="怀柔区"/>
    <moqui.basic.Geo geoId="CHN_11_16" geoTypeEnumId="GEOT_CITY" geoNameLocal="平谷区"/>
    <moqui.basic.Geo geoId="CHN_11_17" geoTypeEnumId="GEOT_CITY" geoNameLocal="密云县"/>
    <moqui.basic.Geo geoId="CHN_11_18" geoTypeEnumId="GEOT_CITY" geoNameLocal="延庆县"/>
    <moqui.basic.Geo geoId="CHN_31_1" geoTypeEnumId="GEOT_CITY" geoNameLocal="黄浦区"/>
    <moqui.basic.Geo geoId="CHN_31_2" geoTypeEnumId="GEOT_CITY" geoNameLocal="卢湾区"/>
    <moqui.basic.Geo geoId="CHN_31_3" geoTypeEnumId="GEOT_CITY" geoNameLocal="徐汇区"/>
    <moqui.basic.Geo geoId="CHN_31_4" geoTypeEnumId="GEOT_CITY" geoNameLocal="长宁区"/>
    <moqui.basic.Geo geoId="CHN_31_5" geoTypeEnumId="GEOT_CITY" geoNameLocal="静安区"/>
    <moqui.basic.Geo geoId="CHN_31_6" geoTypeEnumId="GEOT_CITY" geoNameLocal="普陀区"/>
    <moqui.basic.Geo geoId="CHN_31_7" geoTypeEnumId="GEOT_CITY" geoNameLocal="闸北区"/>
    <moqui.basic.Geo geoId="CHN_31_8" geoTypeEnumId="GEOT_CITY" geoNameLocal="虹口区"/>
    <moqui.basic.Geo geoId="CHN_31_9" geoTypeEnumId="GEOT_CITY" geoNameLocal="杨浦区"/>
    <moqui.basic.Geo geoId="CHN_31_10" geoTypeEnumId="GEOT_CITY" geoNameLocal="闵行区"/>
    <moqui.basic.Geo geoId="CHN_31_11" geoTypeEnumId="GEOT_CITY" geoNameLocal="宝山区"/>
    <moqui.basic.Geo geoId="CHN_31_12" geoTypeEnumId="GEOT_CITY" geoNameLocal="嘉定区"/>
    <moqui.basic.Geo geoId="CHN_31_13" geoTypeEnumId="GEOT_CITY" geoNameLocal="浦东新区"/>
    <moqui.basic.Geo geoId="CHN_31_14" geoTypeEnumId="GEOT_CITY" geoNameLocal="金山区"/>
    <moqui.basic.Geo geoId="CHN_31_15" geoTypeEnumId="GEOT_CITY" geoNameLocal="松江区"/>
    <moqui.basic.Geo geoId="CHN_31_16" geoTypeEnumId="GEOT_CITY" geoNameLocal="青浦区"/>
    <moqui.basic.Geo geoId="CHN_31_17" geoTypeEnumId="GEOT_CITY" geoNameLocal="南汇区"/>
    <moqui.basic.Geo geoId="CHN_31_18" geoTypeEnumId="GEOT_CITY" geoNameLocal="奉贤区"/>
    <moqui.basic.Geo geoId="CHN_31_19" geoTypeEnumId="GEOT_CITY" geoNameLocal="崇明县"/>
    <moqui.basic.Geo geoId="CHN_12_1" geoTypeEnumId="GEOT_CITY" geoNameLocal="和平区"/>
    <moqui.basic.Geo geoId="CHN_12_2" geoTypeEnumId="GEOT_CITY" geoNameLocal="河东区"/>
    <moqui.basic.Geo geoId="CHN_12_3" geoTypeEnumId="GEOT_CITY" geoNameLocal="河西区"/>
    <moqui.basic.Geo geoId="CHN_12_4" geoTypeEnumId="GEOT_CITY" geoNameLocal="南开区"/>
    <moqui.basic.Geo geoId="CHN_12_5" geoTypeEnumId="GEOT_CITY" geoNameLocal="河北区"/>
    <moqui.basic.Geo geoId="CHN_12_6" geoTypeEnumId="GEOT_CITY" geoNameLocal="红桥区"/>
    <moqui.basic.Geo geoId="CHN_12_7" geoTypeEnumId="GEOT_CITY" geoNameLocal="塘沽区"/>
    <moqui.basic.Geo geoId="CHN_12_8" geoTypeEnumId="GEOT_CITY" geoNameLocal="汉沽区"/>
    <moqui.basic.Geo geoId="CHN_12_9" geoTypeEnumId="GEOT_CITY" geoNameLocal="大港区"/>
    <moqui.basic.Geo geoId="CHN_12_10" geoTypeEnumId="GEOT_CITY" geoNameLocal="东丽区"/>
    <moqui.basic.Geo geoId="CHN_12_11" geoTypeEnumId="GEOT_CITY" geoNameLocal="西青区"/>
    <moqui.basic.Geo geoId="CHN_12_12" geoTypeEnumId="GEOT_CITY" geoNameLocal="津南区"/>
    <moqui.basic.Geo geoId="CHN_12_13" geoTypeEnumId="GEOT_CITY" geoNameLocal="北辰区"/>
    <moqui.basic.Geo geoId="CHN_12_14" geoTypeEnumId="GEOT_CITY" geoNameLocal="武清区"/>
    <moqui.basic.Geo geoId="CHN_12_15" geoTypeEnumId="GEOT_CITY" geoNameLocal="宝坻区"/>
    <moqui.basic.Geo geoId="CHN_12_16" geoTypeEnumId="GEOT_CITY" geoNameLocal="宁河县"/>
    <moqui.basic.Geo geoId="CHN_12_17" geoTypeEnumId="GEOT_CITY" geoNameLocal="静海县"/>
    <moqui.basic.Geo geoId="CHN_12_18" geoTypeEnumId="GEOT_CITY" geoNameLocal="蓟县"/>
    <moqui.basic.Geo geoId="CHN_50_1" geoTypeEnumId="GEOT_CITY" geoNameLocal="万州区"/>
    <moqui.basic.Geo geoId="CHN_50_2" geoTypeEnumId="GEOT_CITY" geoNameLocal="涪陵区"/>
    <moqui.basic.Geo geoId="CHN_50_3" geoTypeEnumId="GEOT_CITY" geoNameLocal="渝中区"/>
    <moqui.basic.Geo geoId="CHN_50_4" geoTypeEnumId="GEOT_CITY" geoNameLocal="大渡口区"/>
    <moqui.basic.Geo geoId="CHN_50_5" geoTypeEnumId="GEOT_CITY" geoNameLocal="江北区"/>
    <moqui.basic.Geo geoId="CHN_50_6" geoTypeEnumId="GEOT_CITY" geoNameLocal="沙坪坝区"/>
    <moqui.basic.Geo geoId="CHN_50_7" geoTypeEnumId="GEOT_CITY" geoNameLocal="九龙坡区"/>
    <moqui.basic.Geo geoId="CHN_50_8" geoTypeEnumId="GEOT_CITY" geoNameLocal="南岸区"/>
    <moqui.basic.Geo geoId="CHN_50_9" geoTypeEnumId="GEOT_CITY" geoNameLocal="北碚区"/>
    <moqui.basic.Geo geoId="CHN_50_10" geoTypeEnumId="GEOT_CITY" geoNameLocal="万盛区"/>
    <moqui.basic.Geo geoId="CHN_50_11" geoTypeEnumId="GEOT_CITY" geoNameLocal="双桥区"/>
    <moqui.basic.Geo geoId="CHN_50_12" geoTypeEnumId="GEOT_CITY" geoNameLocal="渝北区"/>
    <moqui.basic.Geo geoId="CHN_50_13" geoTypeEnumId="GEOT_CITY" geoNameLocal="巴南区"/>
    <moqui.basic.Geo geoId="CHN_50_14" geoTypeEnumId="GEOT_CITY" geoNameLocal="黔江区"/>
    <moqui.basic.Geo geoId="CHN_50_15" geoTypeEnumId="GEOT_CITY" geoNameLocal="长寿区"/>
    <moqui.basic.Geo geoId="CHN_50_16" geoTypeEnumId="GEOT_CITY" geoNameLocal="江津区"/>
    <moqui.basic.Geo geoId="CHN_50_17" geoTypeEnumId="GEOT_CITY" geoNameLocal="合川区"/>
    <moqui.basic.Geo geoId="CHN_50_18" geoTypeEnumId="GEOT_CITY" geoNameLocal="永川区"/>
    <moqui.basic.Geo geoId="CHN_50_19" geoTypeEnumId="GEOT_CITY" geoNameLocal="南川区"/>
    <moqui.basic.Geo geoId="CHN_50_20" geoTypeEnumId="GEOT_CITY" geoNameLocal="綦江县"/>
    <moqui.basic.Geo geoId="CHN_50_21" geoTypeEnumId="GEOT_CITY" geoNameLocal="潼南县"/>
    <moqui.basic.Geo geoId="CHN_50_22" geoTypeEnumId="GEOT_CITY" geoNameLocal="铜梁县"/>
    <moqui.basic.Geo geoId="CHN_50_23" geoTypeEnumId="GEOT_CITY" geoNameLocal="大足县"/>
    <moqui.basic.Geo geoId="CHN_50_24" geoTypeEnumId="GEOT_CITY" geoNameLocal="荣昌县"/>
    <moqui.basic.Geo geoId="CHN_50_25" geoTypeEnumId="GEOT_CITY" geoNameLocal="璧山县"/>
    <moqui.basic.Geo geoId="CHN_50_26" geoTypeEnumId="GEOT_CITY" geoNameLocal="梁平县"/>
    <moqui.basic.Geo geoId="CHN_50_27" geoTypeEnumId="GEOT_CITY" geoNameLocal="城口县"/>
    <moqui.basic.Geo geoId="CHN_50_28" geoTypeEnumId="GEOT_CITY" geoNameLocal="丰都县"/>
    <moqui.basic.Geo geoId="CHN_50_29" geoTypeEnumId="GEOT_CITY" geoNameLocal="垫江县"/>
    <moqui.basic.Geo geoId="CHN_50_30" geoTypeEnumId="GEOT_CITY" geoNameLocal="武隆县"/>
    <moqui.basic.Geo geoId="CHN_50_31" geoTypeEnumId="GEOT_CITY" geoNameLocal="忠县"/>
    <moqui.basic.Geo geoId="CHN_50_32" geoTypeEnumId="GEOT_CITY" geoNameLocal="开县"/>
    <moqui.basic.Geo geoId="CHN_50_33" geoTypeEnumId="GEOT_CITY" geoNameLocal="云阳县"/>
    <moqui.basic.Geo geoId="CHN_50_34" geoTypeEnumId="GEOT_CITY" geoNameLocal="奉节县"/>
    <moqui.basic.Geo geoId="CHN_50_35" geoTypeEnumId="GEOT_CITY" geoNameLocal="巫山县"/>
    <moqui.basic.Geo geoId="CHN_50_36" geoTypeEnumId="GEOT_CITY" geoNameLocal="巫溪县"/>
    <moqui.basic.Geo geoId="CHN_50_37" geoTypeEnumId="GEOT_CITY" geoNameLocal="石柱土家族自治县"/>
    <moqui.basic.Geo geoId="CHN_50_38" geoTypeEnumId="GEOT_CITY" geoNameLocal="秀山土家族苗族自治县"/>
    <moqui.basic.Geo geoId="CHN_50_39" geoTypeEnumId="GEOT_CITY" geoNameLocal="酉阳土家族苗族自治县"/>
    <moqui.basic.Geo geoId="CHN_50_40" geoTypeEnumId="GEOT_CITY" geoNameLocal="彭水苗族土家族自治县"/>
    <moqui.basic.Geo geoId="CHN_23_1" geoTypeEnumId="GEOT_CITY" geoNameLocal="哈尔滨市"/>
    <moqui.basic.Geo geoId="CHN_23_2" geoTypeEnumId="GEOT_CITY" geoNameLocal="齐齐哈尔市"/>
    <moqui.basic.Geo geoId="CHN_23_3" geoTypeEnumId="GEOT_CITY" geoNameLocal="鸡西市"/>
    <moqui.basic.Geo geoId="CHN_23_4" geoTypeEnumId="GEOT_CITY" geoNameLocal="鹤岗市"/>
    <moqui.basic.Geo geoId="CHN_23_5" geoTypeEnumId="GEOT_CITY" geoNameLocal="双鸭山市"/>
    <moqui.basic.Geo geoId="CHN_23_6" geoTypeEnumId="GEOT_CITY" geoNameLocal="大庆市"/>
    <moqui.basic.Geo geoId="CHN_23_7" geoTypeEnumId="GEOT_CITY" geoNameLocal="伊春市"/>
    <moqui.basic.Geo geoId="CHN_23_8" geoTypeEnumId="GEOT_CITY" geoNameLocal="佳木斯市"/>
    <moqui.basic.Geo geoId="CHN_23_9" geoTypeEnumId="GEOT_CITY" geoNameLocal="七台河市"/>
    <moqui.basic.Geo geoId="CHN_23_10" geoTypeEnumId="GEOT_CITY" geoNameLocal="牡丹江市"/>
    <moqui.basic.Geo geoId="CHN_23_11" geoTypeEnumId="GEOT_CITY" geoNameLocal="黑河市"/>
    <moqui.basic.Geo geoId="CHN_23_12" geoTypeEnumId="GEOT_CITY" geoNameLocal="绥化市"/>
    <moqui.basic.Geo geoId="CHN_23_13" geoTypeEnumId="GEOT_CITY" geoNameLocal="大兴安岭地区"/>
    <moqui.basic.Geo geoId="CHN_22_1" geoTypeEnumId="GEOT_CITY" geoNameLocal="长春市"/>
    <moqui.basic.Geo geoId="CHN_22_2" geoTypeEnumId="GEOT_CITY" geoNameLocal="吉林市"/>
    <moqui.basic.Geo geoId="CHN_22_3" geoTypeEnumId="GEOT_CITY" geoNameLocal="四平市"/>
    <moqui.basic.Geo geoId="CHN_22_4" geoTypeEnumId="GEOT_CITY" geoNameLocal="辽源市"/>
    <moqui.basic.Geo geoId="CHN_22_5" geoTypeEnumId="GEOT_CITY" geoNameLocal="通化市"/>
    <moqui.basic.Geo geoId="CHN_22_6" geoTypeEnumId="GEOT_CITY" geoNameLocal="白山市"/>
    <moqui.basic.Geo geoId="CHN_22_7" geoTypeEnumId="GEOT_CITY" geoNameLocal="松原市"/>
    <moqui.basic.Geo geoId="CHN_22_8" geoTypeEnumId="GEOT_CITY" geoNameLocal="白城市"/>
    <moqui.basic.Geo geoId="CHN_22_9" geoTypeEnumId="GEOT_CITY" geoNameLocal="延边朝鲜族自治州"/>
    <moqui.basic.Geo geoId="CHN_21_1" geoTypeEnumId="GEOT_CITY" geoNameLocal="沈阳市"/>
    <moqui.basic.Geo geoId="CHN_21_2" geoTypeEnumId="GEOT_CITY" geoNameLocal="大连市"/>
    <moqui.basic.Geo geoId="CHN_21_3" geoTypeEnumId="GEOT_CITY" geoNameLocal="鞍山市"/>
    <moqui.basic.Geo geoId="CHN_21_4" geoTypeEnumId="GEOT_CITY" geoNameLocal="抚顺市"/>
    <moqui.basic.Geo geoId="CHN_21_5" geoTypeEnumId="GEOT_CITY" geoNameLocal="本溪市"/>
    <moqui.basic.Geo geoId="CHN_21_6" geoTypeEnumId="GEOT_CITY" geoNameLocal="丹东市"/>
    <moqui.basic.Geo geoId="CHN_21_7" geoTypeEnumId="GEOT_CITY" geoNameLocal="锦州市"/>
    <moqui.basic.Geo geoId="CHN_21_8" geoTypeEnumId="GEOT_CITY" geoNameLocal="营口市"/>
    <moqui.basic.Geo geoId="CHN_21_9" geoTypeEnumId="GEOT_CITY" geoNameLocal="阜新市"/>
    <moqui.basic.Geo geoId="CHN_21_10" geoTypeEnumId="GEOT_CITY" geoNameLocal="辽阳市"/>
    <moqui.basic.Geo geoId="CHN_21_11" geoTypeEnumId="GEOT_CITY" geoNameLocal="盘锦市"/>
    <moqui.basic.Geo geoId="CHN_21_12" geoTypeEnumId="GEOT_CITY" geoNameLocal="铁岭市"/>
    <moqui.basic.Geo geoId="CHN_21_13" geoTypeEnumId="GEOT_CITY" geoNameLocal="朝阳市"/>
    <moqui.basic.Geo geoId="CHN_21_14" geoTypeEnumId="GEOT_CITY" geoNameLocal="葫芦岛市"/>
    <moqui.basic.Geo geoId="CHN_37_1" geoTypeEnumId="GEOT_CITY" geoNameLocal="济南市"/>
    <moqui.basic.Geo geoId="CHN_37_2" geoTypeEnumId="GEOT_CITY" geoNameLocal="青岛市"/>
    <moqui.basic.Geo geoId="CHN_37_3" geoTypeEnumId="GEOT_CITY" geoNameLocal="淄博市"/>
    <moqui.basic.Geo geoId="CHN_37_4" geoTypeEnumId="GEOT_CITY" geoNameLocal="枣庄市"/>
    <moqui.basic.Geo geoId="CHN_37_5" geoTypeEnumId="GEOT_CITY" geoNameLocal="东营市"/>
    <moqui.basic.Geo geoId="CHN_37_6" geoTypeEnumId="GEOT_CITY" geoNameLocal="烟台市"/>
    <moqui.basic.Geo geoId="CHN_37_7" geoTypeEnumId="GEOT_CITY" geoNameLocal="潍坊市"/>
    <moqui.basic.Geo geoId="CHN_37_8" geoTypeEnumId="GEOT_CITY" geoNameLocal="济宁市"/>
    <moqui.basic.Geo geoId="CHN_37_9" geoTypeEnumId="GEOT_CITY" geoNameLocal="泰安市"/>
    <moqui.basic.Geo geoId="CHN_37_10" geoTypeEnumId="GEOT_CITY" geoNameLocal="威海市"/>
    <moqui.basic.Geo geoId="CHN_37_11" geoTypeEnumId="GEOT_CITY" geoNameLocal="日照市"/>
    <moqui.basic.Geo geoId="CHN_37_12" geoTypeEnumId="GEOT_CITY" geoNameLocal="莱芜市"/>
    <moqui.basic.Geo geoId="CHN_37_13" geoTypeEnumId="GEOT_CITY" geoNameLocal="临沂市"/>
    <moqui.basic.Geo geoId="CHN_37_14" geoTypeEnumId="GEOT_CITY" geoNameLocal="德州市"/>
    <moqui.basic.Geo geoId="CHN_37_15" geoTypeEnumId="GEOT_CITY" geoNameLocal="聊城市"/>
    <moqui.basic.Geo geoId="CHN_37_16" geoTypeEnumId="GEOT_CITY" geoNameLocal="滨州市"/>
    <moqui.basic.Geo geoId="CHN_37_17" geoTypeEnumId="GEOT_CITY" geoNameLocal="菏泽市"/>
    <moqui.basic.Geo geoId="CHN_14_1" geoTypeEnumId="GEOT_CITY" geoNameLocal="太原市"/>
    <moqui.basic.Geo geoId="CHN_14_2" geoTypeEnumId="GEOT_CITY" geoNameLocal="大同市"/>
    <moqui.basic.Geo geoId="CHN_14_3" geoTypeEnumId="GEOT_CITY" geoNameLocal="阳泉市"/>
    <moqui.basic.Geo geoId="CHN_14_4" geoTypeEnumId="GEOT_CITY" geoNameLocal="长治市"/>
    <moqui.basic.Geo geoId="CHN_14_5" geoTypeEnumId="GEOT_CITY" geoNameLocal="晋城市"/>
    <moqui.basic.Geo geoId="CHN_14_6" geoTypeEnumId="GEOT_CITY" geoNameLocal="朔州市"/>
    <moqui.basic.Geo geoId="CHN_14_7" geoTypeEnumId="GEOT_CITY" geoNameLocal="晋中市"/>
    <moqui.basic.Geo geoId="CHN_14_8" geoTypeEnumId="GEOT_CITY" geoNameLocal="运城市"/>
    <moqui.basic.Geo geoId="CHN_14_9" geoTypeEnumId="GEOT_CITY" geoNameLocal="忻州市"/>
    <moqui.basic.Geo geoId="CHN_14_10" geoTypeEnumId="GEOT_CITY" geoNameLocal="临汾市"/>
    <moqui.basic.Geo geoId="CHN_14_11" geoTypeEnumId="GEOT_CITY" geoNameLocal="吕梁市"/>
    <moqui.basic.Geo geoId="CHN_61_1" geoTypeEnumId="GEOT_CITY" geoNameLocal="西安市"/>
    <moqui.basic.Geo geoId="CHN_61_2" geoTypeEnumId="GEOT_CITY" geoNameLocal="铜川市"/>
    <moqui.basic.Geo geoId="CHN_61_3" geoTypeEnumId="GEOT_CITY" geoNameLocal="宝鸡市"/>
    <moqui.basic.Geo geoId="CHN_61_4" geoTypeEnumId="GEOT_CITY" geoNameLocal="咸阳市"/>
    <moqui.basic.Geo geoId="CHN_61_5" geoTypeEnumId="GEOT_CITY" geoNameLocal="渭南市"/>
    <moqui.basic.Geo geoId="CHN_61_6" geoTypeEnumId="GEOT_CITY" geoNameLocal="延安市"/>
    <moqui.basic.Geo geoId="CHN_61_7" geoTypeEnumId="GEOT_CITY" geoNameLocal="汉中市"/>
    <moqui.basic.Geo geoId="CHN_61_8" geoTypeEnumId="GEOT_CITY" geoNameLocal="榆林市"/>
    <moqui.basic.Geo geoId="CHN_61_9" geoTypeEnumId="GEOT_CITY" geoNameLocal="安康市"/>
    <moqui.basic.Geo geoId="CHN_61_10" geoTypeEnumId="GEOT_CITY" geoNameLocal="商洛市"/>
    <moqui.basic.Geo geoId="CHN_13_1" geoTypeEnumId="GEOT_CITY" geoNameLocal="石家庄市"/>
    <moqui.basic.Geo geoId="CHN_13_2" geoTypeEnumId="GEOT_CITY" geoNameLocal="唐山市"/>
    <moqui.basic.Geo geoId="CHN_13_3" geoTypeEnumId="GEOT_CITY" geoNameLocal="秦皇岛市"/>
    <moqui.basic.Geo geoId="CHN_13_4" geoTypeEnumId="GEOT_CITY" geoNameLocal="邯郸市"/>
    <moqui.basic.Geo geoId="CHN_13_5" geoTypeEnumId="GEOT_CITY" geoNameLocal="邢台市"/>
    <moqui.basic.Geo geoId="CHN_13_6" geoTypeEnumId="GEOT_CITY" geoNameLocal="保定市"/>
    <moqui.basic.Geo geoId="CHN_13_7" geoTypeEnumId="GEOT_CITY" geoNameLocal="张家口市"/>
    <moqui.basic.Geo geoId="CHN_13_8" geoTypeEnumId="GEOT_CITY" geoNameLocal="承德市"/>
    <moqui.basic.Geo geoId="CHN_13_9" geoTypeEnumId="GEOT_CITY" geoNameLocal="沧州市"/>
    <moqui.basic.Geo geoId="CHN_13_10" geoTypeEnumId="GEOT_CITY" geoNameLocal="廊坊市"/>
    <moqui.basic.Geo geoId="CHN_13_11" geoTypeEnumId="GEOT_CITY" geoNameLocal="衡水市"/>
    <moqui.basic.Geo geoId="CHN_41_1" geoTypeEnumId="GEOT_CITY" geoNameLocal="郑州市"/>
    <moqui.basic.Geo geoId="CHN_41_2" geoTypeEnumId="GEOT_CITY" geoNameLocal="开封市"/>
    <moqui.basic.Geo geoId="CHN_41_3" geoTypeEnumId="GEOT_CITY" geoNameLocal="洛阳市"/>
    <moqui.basic.Geo geoId="CHN_41_4" geoTypeEnumId="GEOT_CITY" geoNameLocal="平顶山市"/>
    <moqui.basic.Geo geoId="CHN_41_5" geoTypeEnumId="GEOT_CITY" geoNameLocal="安阳市"/>
    <moqui.basic.Geo geoId="CHN_41_6" geoTypeEnumId="GEOT_CITY" geoNameLocal="鹤壁市"/>
    <moqui.basic.Geo geoId="CHN_41_7" geoTypeEnumId="GEOT_CITY" geoNameLocal="新乡市"/>
    <moqui.basic.Geo geoId="CHN_41_8" geoTypeEnumId="GEOT_CITY" geoNameLocal="焦作市"/>
    <moqui.basic.Geo geoId="CHN_41_9" geoTypeEnumId="GEOT_CITY" geoNameLocal="济源市"/>
    <moqui.basic.Geo geoId="CHN_41_10" geoTypeEnumId="GEOT_CITY" geoNameLocal="濮阳市"/>
    <moqui.basic.Geo geoId="CHN_41_11" geoTypeEnumId="GEOT_CITY" geoNameLocal="许昌市"/>
    <moqui.basic.Geo geoId="CHN_41_12" geoTypeEnumId="GEOT_CITY" geoNameLocal="漯河市"/>
    <moqui.basic.Geo geoId="CHN_41_13" geoTypeEnumId="GEOT_CITY" geoNameLocal="三门峡市"/>
    <moqui.basic.Geo geoId="CHN_41_14" geoTypeEnumId="GEOT_CITY" geoNameLocal="南阳市"/>
    <moqui.basic.Geo geoId="CHN_41_15" geoTypeEnumId="GEOT_CITY" geoNameLocal="商丘市"/>
    <moqui.basic.Geo geoId="CHN_41_16" geoTypeEnumId="GEOT_CITY" geoNameLocal="信阳市"/>
    <moqui.basic.Geo geoId="CHN_41_17" geoTypeEnumId="GEOT_CITY" geoNameLocal="周口市"/>
    <moqui.basic.Geo geoId="CHN_41_18" geoTypeEnumId="GEOT_CITY" geoNameLocal="驻马店市"/>
    <moqui.basic.Geo geoId="CHN_42_1" geoTypeEnumId="GEOT_CITY" geoNameLocal="武汉市"/>
    <moqui.basic.Geo geoId="CHN_42_2" geoTypeEnumId="GEOT_CITY" geoNameLocal="黄石市"/>
    <moqui.basic.Geo geoId="CHN_42_3" geoTypeEnumId="GEOT_CITY" geoNameLocal="十堰市"/>
    <moqui.basic.Geo geoId="CHN_42_4" geoTypeEnumId="GEOT_CITY" geoNameLocal="宜昌市"/>
    <moqui.basic.Geo geoId="CHN_42_5" geoTypeEnumId="GEOT_CITY" geoNameLocal="襄樊市"/>
    <moqui.basic.Geo geoId="CHN_42_6" geoTypeEnumId="GEOT_CITY" geoNameLocal="鄂州市"/>
    <moqui.basic.Geo geoId="CHN_42_7" geoTypeEnumId="GEOT_CITY" geoNameLocal="荆门市"/>
    <moqui.basic.Geo geoId="CHN_42_8" geoTypeEnumId="GEOT_CITY" geoNameLocal="孝感市"/>
    <moqui.basic.Geo geoId="CHN_42_9" geoTypeEnumId="GEOT_CITY" geoNameLocal="荆州市"/>
    <moqui.basic.Geo geoId="CHN_42_10" geoTypeEnumId="GEOT_CITY" geoNameLocal="黄冈市"/>
    <moqui.basic.Geo geoId="CHN_42_11" geoTypeEnumId="GEOT_CITY" geoNameLocal="咸宁市"/>
    <moqui.basic.Geo geoId="CHN_42_12" geoTypeEnumId="GEOT_CITY" geoNameLocal="随州市"/>
    <moqui.basic.Geo geoId="CHN_42_13" geoTypeEnumId="GEOT_CITY" geoNameLocal="恩施土家族苗族自治州"/>
    <moqui.basic.Geo geoId="CHN_42_14" geoTypeEnumId="GEOT_CITY" geoNameLocal="仙桃市"/>
    <moqui.basic.Geo geoId="CHN_42_15" geoTypeEnumId="GEOT_CITY" geoNameLocal="潜江市"/>
    <moqui.basic.Geo geoId="CHN_42_16" geoTypeEnumId="GEOT_CITY" geoNameLocal="天门市"/>
    <moqui.basic.Geo geoId="CHN_42_17" geoTypeEnumId="GEOT_CITY" geoNameLocal="神农架林区"/>
    <moqui.basic.Geo geoId="CHN_43_1" geoTypeEnumId="GEOT_CITY" geoNameLocal="长沙市"/>
    <moqui.basic.Geo geoId="CHN_43_2" geoTypeEnumId="GEOT_CITY" geoNameLocal="株洲市"/>
    <moqui.basic.Geo geoId="CHN_43_3" geoTypeEnumId="GEOT_CITY" geoNameLocal="湘潭市"/>
    <moqui.basic.Geo geoId="CHN_43_4" geoTypeEnumId="GEOT_CITY" geoNameLocal="衡阳市"/>
    <moqui.basic.Geo geoId="CHN_43_5" geoTypeEnumId="GEOT_CITY" geoNameLocal="邵阳市"/>
    <moqui.basic.Geo geoId="CHN_43_6" geoTypeEnumId="GEOT_CITY" geoNameLocal="岳阳市"/>
    <moqui.basic.Geo geoId="CHN_43_7" geoTypeEnumId="GEOT_CITY" geoNameLocal="常德市"/>
    <moqui.basic.Geo geoId="CHN_43_8" geoTypeEnumId="GEOT_CITY" geoNameLocal="张家界市"/>
    <moqui.basic.Geo geoId="CHN_43_9" geoTypeEnumId="GEOT_CITY" geoNameLocal="益阳市"/>
    <moqui.basic.Geo geoId="CHN_43_10" geoTypeEnumId="GEOT_CITY" geoNameLocal="郴州市"/>
    <moqui.basic.Geo geoId="CHN_43_11" geoTypeEnumId="GEOT_CITY" geoNameLocal="永州市"/>
    <moqui.basic.Geo geoId="CHN_43_12" geoTypeEnumId="GEOT_CITY" geoNameLocal="怀化市"/>
    <moqui.basic.Geo geoId="CHN_43_13" geoTypeEnumId="GEOT_CITY" geoNameLocal="娄底市"/>
    <moqui.basic.Geo geoId="CHN_43_14" geoTypeEnumId="GEOT_CITY" geoNameLocal="湘西土家族苗族自治州"/>
    <moqui.basic.Geo geoId="CHN_46_1" geoTypeEnumId="GEOT_CITY" geoNameLocal="海口市"/>
    <moqui.basic.Geo geoId="CHN_46_2" geoTypeEnumId="GEOT_CITY" geoNameLocal="三亚市"/>
    <moqui.basic.Geo geoId="CHN_46_3" geoTypeEnumId="GEOT_CITY" geoNameLocal="五指山市"/>
    <moqui.basic.Geo geoId="CHN_46_4" geoTypeEnumId="GEOT_CITY" geoNameLocal="琼海市"/>
    <moqui.basic.Geo geoId="CHN_46_5" geoTypeEnumId="GEOT_CITY" geoNameLocal="儋州市"/>
    <moqui.basic.Geo geoId="CHN_46_6" geoTypeEnumId="GEOT_CITY" geoNameLocal="文昌市"/>
    <moqui.basic.Geo geoId="CHN_46_7" geoTypeEnumId="GEOT_CITY" geoNameLocal="万宁市"/>
    <moqui.basic.Geo geoId="CHN_46_8" geoTypeEnumId="GEOT_CITY" geoNameLocal="东方市"/>
    <moqui.basic.Geo geoId="CHN_46_9" geoTypeEnumId="GEOT_CITY" geoNameLocal="定安县"/>
    <moqui.basic.Geo geoId="CHN_46_10" geoTypeEnumId="GEOT_CITY" geoNameLocal="屯昌县"/>
    <moqui.basic.Geo geoId="CHN_46_11" geoTypeEnumId="GEOT_CITY" geoNameLocal="澄迈县"/>
    <moqui.basic.Geo geoId="CHN_46_12" geoTypeEnumId="GEOT_CITY" geoNameLocal="临高县"/>
    <moqui.basic.Geo geoId="CHN_46_13" geoTypeEnumId="GEOT_CITY" geoNameLocal="白沙黎族自治县"/>
    <moqui.basic.Geo geoId="CHN_46_14" geoTypeEnumId="GEOT_CITY" geoNameLocal="昌江黎族自治县"/>
    <moqui.basic.Geo geoId="CHN_46_15" geoTypeEnumId="GEOT_CITY" geoNameLocal="乐东黎族自治县"/>
    <moqui.basic.Geo geoId="CHN_46_16" geoTypeEnumId="GEOT_CITY" geoNameLocal="陵水黎族自治县"/>
    <moqui.basic.Geo geoId="CHN_46_17" geoTypeEnumId="GEOT_CITY" geoNameLocal="保亭黎族苗族自治县"/>
    <moqui.basic.Geo geoId="CHN_46_18" geoTypeEnumId="GEOT_CITY" geoNameLocal="琼中黎族苗族自治县"/>
    <moqui.basic.Geo geoId="CHN_32_1" geoTypeEnumId="GEOT_CITY" geoNameLocal="南京市"/>
    <moqui.basic.Geo geoId="CHN_32_2" geoTypeEnumId="GEOT_CITY" geoNameLocal="无锡市"/>
    <moqui.basic.Geo geoId="CHN_32_3" geoTypeEnumId="GEOT_CITY" geoNameLocal="徐州市"/>
    <moqui.basic.Geo geoId="CHN_32_4" geoTypeEnumId="GEOT_CITY" geoNameLocal="常州市"/>
    <moqui.basic.Geo geoId="CHN_32_5" geoTypeEnumId="GEOT_CITY" geoNameLocal="苏州市"/>
    <moqui.basic.Geo geoId="CHN_32_6" geoTypeEnumId="GEOT_CITY" geoNameLocal="南通市"/>
    <moqui.basic.Geo geoId="CHN_32_7" geoTypeEnumId="GEOT_CITY" geoNameLocal="连云港市"/>
    <moqui.basic.Geo geoId="CHN_32_8" geoTypeEnumId="GEOT_CITY" geoNameLocal="淮安市"/>
    <moqui.basic.Geo geoId="CHN_32_9" geoTypeEnumId="GEOT_CITY" geoNameLocal="盐城市"/>
    <moqui.basic.Geo geoId="CHN_32_10" geoTypeEnumId="GEOT_CITY" geoNameLocal="扬州市"/>
    <moqui.basic.Geo geoId="CHN_32_11" geoTypeEnumId="GEOT_CITY" geoNameLocal="镇江市"/>
    <moqui.basic.Geo geoId="CHN_32_12" geoTypeEnumId="GEOT_CITY" geoNameLocal="泰州市"/>
    <moqui.basic.Geo geoId="CHN_32_13" geoTypeEnumId="GEOT_CITY" geoNameLocal="宿迁市"/>
    <moqui.basic.Geo geoId="CHN_36_1" geoTypeEnumId="GEOT_CITY" geoNameLocal="南昌市"/>
    <moqui.basic.Geo geoId="CHN_36_2" geoTypeEnumId="GEOT_CITY" geoNameLocal="景德镇市"/>
    <moqui.basic.Geo geoId="CHN_36_3" geoTypeEnumId="GEOT_CITY" geoNameLocal="萍乡市"/>
    <moqui.basic.Geo geoId="CHN_36_4" geoTypeEnumId="GEOT_CITY" geoNameLocal="九江市"/>
    <moqui.basic.Geo geoId="CHN_36_5" geoTypeEnumId="GEOT_CITY" geoNameLocal="新余市"/>
    <moqui.basic.Geo geoId="CHN_36_6" geoTypeEnumId="GEOT_CITY" geoNameLocal="鹰潭市"/>
    <moqui.basic.Geo geoId="CHN_36_7" geoTypeEnumId="GEOT_CITY" geoNameLocal="赣州市"/>
    <moqui.basic.Geo geoId="CHN_36_8" geoTypeEnumId="GEOT_CITY" geoNameLocal="吉安市"/>
    <moqui.basic.Geo geoId="CHN_36_9" geoTypeEnumId="GEOT_CITY" geoNameLocal="宜春市"/>
    <moqui.basic.Geo geoId="CHN_36_10" geoTypeEnumId="GEOT_CITY" geoNameLocal="抚州市"/>
    <moqui.basic.Geo geoId="CHN_36_11" geoTypeEnumId="GEOT_CITY" geoNameLocal="上饶市"/>
    <moqui.basic.Geo geoId="CHN_44_1" geoTypeEnumId="GEOT_CITY" geoNameLocal="广州市"/>
    <moqui.basic.Geo geoId="CHN_44_2" geoTypeEnumId="GEOT_CITY" geoNameLocal="韶关市"/>
    <moqui.basic.Geo geoId="CHN_44_3" geoTypeEnumId="GEOT_CITY" geoNameLocal="深圳市"/>
    <moqui.basic.Geo geoId="CHN_44_4" geoTypeEnumId="GEOT_CITY" geoNameLocal="珠海市"/>
    <moqui.basic.Geo geoId="CHN_44_5" geoTypeEnumId="GEOT_CITY" geoNameLocal="汕头市"/>
    <moqui.basic.Geo geoId="CHN_44_6" geoTypeEnumId="GEOT_CITY" geoNameLocal="佛山市"/>
    <moqui.basic.Geo geoId="CHN_44_7" geoTypeEnumId="GEOT_CITY" geoNameLocal="江门市"/>
    <moqui.basic.Geo geoId="CHN_44_8" geoTypeEnumId="GEOT_CITY" geoNameLocal="湛江市"/>
    <moqui.basic.Geo geoId="CHN_44_9" geoTypeEnumId="GEOT_CITY" geoNameLocal="茂名市"/>
    <moqui.basic.Geo geoId="CHN_44_10" geoTypeEnumId="GEOT_CITY" geoNameLocal="肇庆市"/>
    <moqui.basic.Geo geoId="CHN_44_11" geoTypeEnumId="GEOT_CITY" geoNameLocal="惠州市"/>
    <moqui.basic.Geo geoId="CHN_44_12" geoTypeEnumId="GEOT_CITY" geoNameLocal="梅州市"/>
    <moqui.basic.Geo geoId="CHN_44_13" geoTypeEnumId="GEOT_CITY" geoNameLocal="汕尾市"/>
    <moqui.basic.Geo geoId="CHN_44_14" geoTypeEnumId="GEOT_CITY" geoNameLocal="河源市"/>
    <moqui.basic.Geo geoId="CHN_44_15" geoTypeEnumId="GEOT_CITY" geoNameLocal="阳江市"/>
    <moqui.basic.Geo geoId="CHN_44_16" geoTypeEnumId="GEOT_CITY" geoNameLocal="清远市"/>
    <moqui.basic.Geo geoId="CHN_44_17" geoTypeEnumId="GEOT_CITY" geoNameLocal="东莞市"/>
    <moqui.basic.Geo geoId="CHN_44_18" geoTypeEnumId="GEOT_CITY" geoNameLocal="中山市"/>
    <moqui.basic.Geo geoId="CHN_44_19" geoTypeEnumId="GEOT_CITY" geoNameLocal="潮州市"/>
    <moqui.basic.Geo geoId="CHN_44_20" geoTypeEnumId="GEOT_CITY" geoNameLocal="揭阳市"/>
    <moqui.basic.Geo geoId="CHN_44_21" geoTypeEnumId="GEOT_CITY" geoNameLocal="云浮市"/>
    <moqui.basic.Geo geoId="CHN_45_1" geoTypeEnumId="GEOT_CITY" geoNameLocal="南宁市"/>
    <moqui.basic.Geo geoId="CHN_45_2" geoTypeEnumId="GEOT_CITY" geoNameLocal="柳州市"/>
    <moqui.basic.Geo geoId="CHN_45_3" geoTypeEnumId="GEOT_CITY" geoNameLocal="桂林市"/>
    <moqui.basic.Geo geoId="CHN_45_4" geoTypeEnumId="GEOT_CITY" geoNameLocal="梧州市"/>
    <moqui.basic.Geo geoId="CHN_45_5" geoTypeEnumId="GEOT_CITY" geoNameLocal="北海市"/>
    <moqui.basic.Geo geoId="CHN_45_6" geoTypeEnumId="GEOT_CITY" geoNameLocal="防城港市"/>
    <moqui.basic.Geo geoId="CHN_45_7" geoTypeEnumId="GEOT_CITY" geoNameLocal="钦州市"/>
    <moqui.basic.Geo geoId="CHN_45_8" geoTypeEnumId="GEOT_CITY" geoNameLocal="贵港市"/>
    <moqui.basic.Geo geoId="CHN_45_9" geoTypeEnumId="GEOT_CITY" geoNameLocal="玉林市"/>
    <moqui.basic.Geo geoId="CHN_45_10" geoTypeEnumId="GEOT_CITY" geoNameLocal="百色市"/>
    <moqui.basic.Geo geoId="CHN_45_11" geoTypeEnumId="GEOT_CITY" geoNameLocal="贺州市"/>
    <moqui.basic.Geo geoId="CHN_45_12" geoTypeEnumId="GEOT_CITY" geoNameLocal="河池市"/>
    <moqui.basic.Geo geoId="CHN_45_13" geoTypeEnumId="GEOT_CITY" geoNameLocal="来宾市"/>
    <moqui.basic.Geo geoId="CHN_45_14" geoTypeEnumId="GEOT_CITY" geoNameLocal="崇左市"/>
    <moqui.basic.Geo geoId="CHN_53_1" geoTypeEnumId="GEOT_CITY" geoNameLocal="昆明市"/>
    <moqui.basic.Geo geoId="CHN_53_2" geoTypeEnumId="GEOT_CITY" geoNameLocal="曲靖市"/>
    <moqui.basic.Geo geoId="CHN_53_3" geoTypeEnumId="GEOT_CITY" geoNameLocal="玉溪市"/>
    <moqui.basic.Geo geoId="CHN_53_4" geoTypeEnumId="GEOT_CITY" geoNameLocal="保山市"/>
    <moqui.basic.Geo geoId="CHN_53_5" geoTypeEnumId="GEOT_CITY" geoNameLocal="昭通市"/>
    <moqui.basic.Geo geoId="CHN_53_6" geoTypeEnumId="GEOT_CITY" geoNameLocal="丽江市"/>
    <moqui.basic.Geo geoId="CHN_53_7" geoTypeEnumId="GEOT_CITY" geoNameLocal="思茅市"/>
    <moqui.basic.Geo geoId="CHN_53_8" geoTypeEnumId="GEOT_CITY" geoNameLocal="临沧市"/>
    <moqui.basic.Geo geoId="CHN_53_9" geoTypeEnumId="GEOT_CITY" geoNameLocal="楚雄彝族自治州"/>
    <moqui.basic.Geo geoId="CHN_53_10" geoTypeEnumId="GEOT_CITY" geoNameLocal="红河哈尼族彝族自治州"/>
    <moqui.basic.Geo geoId="CHN_53_11" geoTypeEnumId="GEOT_CITY" geoNameLocal="文山壮族苗族自治州"/>
    <moqui.basic.Geo geoId="CHN_53_12" geoTypeEnumId="GEOT_CITY" geoNameLocal="西双版纳傣族自治州"/>
    <moqui.basic.Geo geoId="CHN_53_13" geoTypeEnumId="GEOT_CITY" geoNameLocal="大理白族自治州"/>
    <moqui.basic.Geo geoId="CHN_53_14" geoTypeEnumId="GEOT_CITY" geoNameLocal="德宏傣族景颇族自治州"/>
    <moqui.basic.Geo geoId="CHN_53_15" geoTypeEnumId="GEOT_CITY" geoNameLocal="怒江傈僳族自治州"/>
    <moqui.basic.Geo geoId="CHN_53_16" geoTypeEnumId="GEOT_CITY" geoNameLocal="迪庆藏族自治州"/>
    <moqui.basic.Geo geoId="CHN_52_1" geoTypeEnumId="GEOT_CITY" geoNameLocal="贵阳市"/>
    <moqui.basic.Geo geoId="CHN_52_2" geoTypeEnumId="GEOT_CITY" geoNameLocal="六盘水市"/>
    <moqui.basic.Geo geoId="CHN_52_3" geoTypeEnumId="GEOT_CITY" geoNameLocal="遵义市"/>
    <moqui.basic.Geo geoId="CHN_52_4" geoTypeEnumId="GEOT_CITY" geoNameLocal="安顺市"/>
    <moqui.basic.Geo geoId="CHN_52_5" geoTypeEnumId="GEOT_CITY" geoNameLocal="铜仁地区"/>
    <moqui.basic.Geo geoId="CHN_52_6" geoTypeEnumId="GEOT_CITY" geoNameLocal="黔西南布依族苗族自治州"/>
    <moqui.basic.Geo geoId="CHN_52_7" geoTypeEnumId="GEOT_CITY" geoNameLocal="毕节地区"/>
    <moqui.basic.Geo geoId="CHN_52_8" geoTypeEnumId="GEOT_CITY" geoNameLocal="黔东南苗族侗族自治州"/>
    <moqui.basic.Geo geoId="CHN_52_9" geoTypeEnumId="GEOT_CITY" geoNameLocal="黔南布依族苗族自治州"/>
    <moqui.basic.Geo geoId="CHN_51_1" geoTypeEnumId="GEOT_CITY" geoNameLocal="成都市"/>
    <moqui.basic.Geo geoId="CHN_51_2" geoTypeEnumId="GEOT_CITY" geoNameLocal="自贡市"/>
    <moqui.basic.Geo geoId="CHN_51_3" geoTypeEnumId="GEOT_CITY" geoNameLocal="攀枝花市"/>
    <moqui.basic.Geo geoId="CHN_51_4" geoTypeEnumId="GEOT_CITY" geoNameLocal="泸州市"/>
    <moqui.basic.Geo geoId="CHN_51_5" geoTypeEnumId="GEOT_CITY" geoNameLocal="德阳市"/>
    <moqui.basic.Geo geoId="CHN_51_6" geoTypeEnumId="GEOT_CITY" geoNameLocal="绵阳市"/>
    <moqui.basic.Geo geoId="CHN_51_7" geoTypeEnumId="GEOT_CITY" geoNameLocal="广元市"/>
    <moqui.basic.Geo geoId="CHN_51_8" geoTypeEnumId="GEOT_CITY" geoNameLocal="遂宁市"/>
    <moqui.basic.Geo geoId="CHN_51_9" geoTypeEnumId="GEOT_CITY" geoNameLocal="内江市"/>
    <moqui.basic.Geo geoId="CHN_51_10" geoTypeEnumId="GEOT_CITY" geoNameLocal="乐山市"/>
    <moqui.basic.Geo geoId="CHN_51_11" geoTypeEnumId="GEOT_CITY" geoNameLocal="南充市"/>
    <moqui.basic.Geo geoId="CHN_51_12" geoTypeEnumId="GEOT_CITY" geoNameLocal="眉山市"/>
    <moqui.basic.Geo geoId="CHN_51_13" geoTypeEnumId="GEOT_CITY" geoNameLocal="宜宾市"/>
    <moqui.basic.Geo geoId="CHN_51_14" geoTypeEnumId="GEOT_CITY" geoNameLocal="广安市"/>
    <moqui.basic.Geo geoId="CHN_51_15" geoTypeEnumId="GEOT_CITY" geoNameLocal="达州市"/>
    <moqui.basic.Geo geoId="CHN_51_16" geoTypeEnumId="GEOT_CITY" geoNameLocal="雅安市"/>
    <moqui.basic.Geo geoId="CHN_51_17" geoTypeEnumId="GEOT_CITY" geoNameLocal="巴中市"/>
    <moqui.basic.Geo geoId="CHN_51_18" geoTypeEnumId="GEOT_CITY" geoNameLocal="资阳市"/>
    <moqui.basic.Geo geoId="CHN_51_19" geoTypeEnumId="GEOT_CITY" geoNameLocal="阿坝藏族羌族自治州"/>
    <moqui.basic.Geo geoId="CHN_51_20" geoTypeEnumId="GEOT_CITY" geoNameLocal="甘孜藏族自治州"/>
    <moqui.basic.Geo geoId="CHN_51_21" geoTypeEnumId="GEOT_CITY" geoNameLocal="凉山彝族自治州"/>
    <moqui.basic.Geo geoId="CHN_15_1" geoTypeEnumId="GEOT_CITY" geoNameLocal="呼和浩特市"/>
    <moqui.basic.Geo geoId="CHN_15_2" geoTypeEnumId="GEOT_CITY" geoNameLocal="包头市"/>
    <moqui.basic.Geo geoId="CHN_15_3" geoTypeEnumId="GEOT_CITY" geoNameLocal="乌海市"/>
    <moqui.basic.Geo geoId="CHN_15_4" geoTypeEnumId="GEOT_CITY" geoNameLocal="赤峰市"/>
    <moqui.basic.Geo geoId="CHN_15_5" geoTypeEnumId="GEOT_CITY" geoNameLocal="通辽市"/>
    <moqui.basic.Geo geoId="CHN_15_6" geoTypeEnumId="GEOT_CITY" geoNameLocal="鄂尔多斯市"/>
    <moqui.basic.Geo geoId="CHN_15_7" geoTypeEnumId="GEOT_CITY" geoNameLocal="呼伦贝尔市"/>
    <moqui.basic.Geo geoId="CHN_15_8" geoTypeEnumId="GEOT_CITY" geoNameLocal="巴彦淖尔市"/>
    <moqui.basic.Geo geoId="CHN_15_9" geoTypeEnumId="GEOT_CITY" geoNameLocal="乌兰察布市"/>
    <moqui.basic.Geo geoId="CHN_15_10" geoTypeEnumId="GEOT_CITY" geoNameLocal="兴安盟"/>
    <moqui.basic.Geo geoId="CHN_15_11" geoTypeEnumId="GEOT_CITY" geoNameLocal="锡林郭勒盟"/>
    <moqui.basic.Geo geoId="CHN_15_12" geoTypeEnumId="GEOT_CITY" geoNameLocal="阿拉善盟"/>
    <moqui.basic.Geo geoId="CHN_64_1" geoTypeEnumId="GEOT_CITY" geoNameLocal="银川市"/>
    <moqui.basic.Geo geoId="CHN_64_2" geoTypeEnumId="GEOT_CITY" geoNameLocal="石嘴山市"/>
    <moqui.basic.Geo geoId="CHN_64_3" geoTypeEnumId="GEOT_CITY" geoNameLocal="吴忠市"/>
    <moqui.basic.Geo geoId="CHN_64_4" geoTypeEnumId="GEOT_CITY" geoNameLocal="固原市"/>
    <moqui.basic.Geo geoId="CHN_64_5" geoTypeEnumId="GEOT_CITY" geoNameLocal="中卫市"/>
    <moqui.basic.Geo geoId="CHN_62_1" geoTypeEnumId="GEOT_CITY" geoNameLocal="兰州市"/>
    <moqui.basic.Geo geoId="CHN_62_2" geoTypeEnumId="GEOT_CITY" geoNameLocal="嘉峪关市"/>
    <moqui.basic.Geo geoId="CHN_62_3" geoTypeEnumId="GEOT_CITY" geoNameLocal="金昌市"/>
    <moqui.basic.Geo geoId="CHN_62_4" geoTypeEnumId="GEOT_CITY" geoNameLocal="白银市"/>
    <moqui.basic.Geo geoId="CHN_62_5" geoTypeEnumId="GEOT_CITY" geoNameLocal="天水市"/>
    <moqui.basic.Geo geoId="CHN_62_6" geoTypeEnumId="GEOT_CITY" geoNameLocal="武威市"/>
    <moqui.basic.Geo geoId="CHN_62_7" geoTypeEnumId="GEOT_CITY" geoNameLocal="张掖市"/>
    <moqui.basic.Geo geoId="CHN_62_8" geoTypeEnumId="GEOT_CITY" geoNameLocal="平凉市"/>
    <moqui.basic.Geo geoId="CHN_62_9" geoTypeEnumId="GEOT_CITY" geoNameLocal="酒泉市"/>
    <moqui.basic.Geo geoId="CHN_62_10" geoTypeEnumId="GEOT_CITY" geoNameLocal="庆阳市"/>
    <moqui.basic.Geo geoId="CHN_62_11" geoTypeEnumId="GEOT_CITY" geoNameLocal="定西市"/>
    <moqui.basic.Geo geoId="CHN_62_12" geoTypeEnumId="GEOT_CITY" geoNameLocal="陇南市"/>
    <moqui.basic.Geo geoId="CHN_62_13" geoTypeEnumId="GEOT_CITY" geoNameLocal="临夏回族自治州"/>
    <moqui.basic.Geo geoId="CHN_62_14" geoTypeEnumId="GEOT_CITY" geoNameLocal="甘南藏族自治州"/>
    <moqui.basic.Geo geoId="CHN_63_1" geoTypeEnumId="GEOT_CITY" geoNameLocal="西宁市"/>
    <moqui.basic.Geo geoId="CHN_63_2" geoTypeEnumId="GEOT_CITY" geoNameLocal="海东地区"/>
    <moqui.basic.Geo geoId="CHN_63_3" geoTypeEnumId="GEOT_CITY" geoNameLocal="海北藏族自治州"/>
    <moqui.basic.Geo geoId="CHN_63_4" geoTypeEnumId="GEOT_CITY" geoNameLocal="黄南藏族自治州"/>
    <moqui.basic.Geo geoId="CHN_63_5" geoTypeEnumId="GEOT_CITY" geoNameLocal="海南藏族自治州"/>
    <moqui.basic.Geo geoId="CHN_63_6" geoTypeEnumId="GEOT_CITY" geoNameLocal="果洛藏族自治州"/>
    <moqui.basic.Geo geoId="CHN_63_7" geoTypeEnumId="GEOT_CITY" geoNameLocal="玉树藏族自治州"/>
    <moqui.basic.Geo geoId="CHN_63_8" geoTypeEnumId="GEOT_CITY" geoNameLocal="海西蒙古族藏族自治州"/>
    <moqui.basic.Geo geoId="CHN_54_1" geoTypeEnumId="GEOT_CITY" geoNameLocal="拉萨市"/>
    <moqui.basic.Geo geoId="CHN_54_2" geoTypeEnumId="GEOT_CITY" geoNameLocal="昌都地区"/>
    <moqui.basic.Geo geoId="CHN_54_3" geoTypeEnumId="GEOT_CITY" geoNameLocal="山南地区"/>
    <moqui.basic.Geo geoId="CHN_54_4" geoTypeEnumId="GEOT_CITY" geoNameLocal="日喀则地区"/>
    <moqui.basic.Geo geoId="CHN_54_5" geoTypeEnumId="GEOT_CITY" geoNameLocal="那曲地区"/>
    <moqui.basic.Geo geoId="CHN_54_6" geoTypeEnumId="GEOT_CITY" geoNameLocal="阿里地区"/>
    <moqui.basic.Geo geoId="CHN_54_7" geoTypeEnumId="GEOT_CITY" geoNameLocal="林芝地区"/>
    <moqui.basic.Geo geoId="CHN_65_1" geoTypeEnumId="GEOT_CITY" geoNameLocal="乌鲁木齐市"/>
    <moqui.basic.Geo geoId="CHN_65_2" geoTypeEnumId="GEOT_CITY" geoNameLocal="克拉玛依市"/>
    <moqui.basic.Geo geoId="CHN_65_3" geoTypeEnumId="GEOT_CITY" geoNameLocal="吐鲁番地区"/>
    <moqui.basic.Geo geoId="CHN_65_4" geoTypeEnumId="GEOT_CITY" geoNameLocal="哈密地区"/>
    <moqui.basic.Geo geoId="CHN_65_5" geoTypeEnumId="GEOT_CITY" geoNameLocal="昌吉回族自治州"/>
    <moqui.basic.Geo geoId="CHN_65_6" geoTypeEnumId="GEOT_CITY" geoNameLocal="博尔塔拉蒙古自治州"/>
    <moqui.basic.Geo geoId="CHN_65_7" geoTypeEnumId="GEOT_CITY" geoNameLocal="巴音郭楞蒙古自治州"/>
    <moqui.basic.Geo geoId="CHN_65_8" geoTypeEnumId="GEOT_CITY" geoNameLocal="阿克苏地区"/>
    <moqui.basic.Geo geoId="CHN_65_9" geoTypeEnumId="GEOT_CITY" geoNameLocal="克孜勒苏柯尔克孜自治州"/>
    <moqui.basic.Geo geoId="CHN_65_10" geoTypeEnumId="GEOT_CITY" geoNameLocal="喀什地区"/>
    <moqui.basic.Geo geoId="CHN_65_11" geoTypeEnumId="GEOT_CITY" geoNameLocal="和田地区"/>
    <moqui.basic.Geo geoId="CHN_65_12" geoTypeEnumId="GEOT_CITY" geoNameLocal="伊犁哈萨克自治州"/>
    <moqui.basic.Geo geoId="CHN_65_13" geoTypeEnumId="GEOT_CITY" geoNameLocal="塔城地区"/>
    <moqui.basic.Geo geoId="CHN_65_14" geoTypeEnumId="GEOT_CITY" geoNameLocal="阿勒泰地区"/>
    <moqui.basic.Geo geoId="CHN_65_15" geoTypeEnumId="GEOT_CITY" geoNameLocal="石河子市"/>
    <moqui.basic.Geo geoId="CHN_65_16" geoTypeEnumId="GEOT_CITY" geoNameLocal="阿拉尔市"/>
    <moqui.basic.Geo geoId="CHN_65_17" geoTypeEnumId="GEOT_CITY" geoNameLocal="图木舒克市"/>
    <moqui.basic.Geo geoId="CHN_65_18" geoTypeEnumId="GEOT_CITY" geoNameLocal="五家渠市"/>
    <moqui.basic.Geo geoId="CHN_34_1" geoTypeEnumId="GEOT_CITY" geoNameLocal="合肥市"/>
    <moqui.basic.Geo geoId="CHN_34_2" geoTypeEnumId="GEOT_CITY" geoNameLocal="芜湖市"/>
    <moqui.basic.Geo geoId="CHN_34_3" geoTypeEnumId="GEOT_CITY" geoNameLocal="蚌埠市"/>
    <moqui.basic.Geo geoId="CHN_34_4" geoTypeEnumId="GEOT_CITY" geoNameLocal="淮南市"/>
    <moqui.basic.Geo geoId="CHN_34_5" geoTypeEnumId="GEOT_CITY" geoNameLocal="马鞍山市"/>
    <moqui.basic.Geo geoId="CHN_34_6" geoTypeEnumId="GEOT_CITY" geoNameLocal="淮北市"/>
    <moqui.basic.Geo geoId="CHN_34_7" geoTypeEnumId="GEOT_CITY" geoNameLocal="铜陵市"/>
    <moqui.basic.Geo geoId="CHN_34_8" geoTypeEnumId="GEOT_CITY" geoNameLocal="安庆市"/>
    <moqui.basic.Geo geoId="CHN_34_9" geoTypeEnumId="GEOT_CITY" geoNameLocal="黄山市"/>
    <moqui.basic.Geo geoId="CHN_34_10" geoTypeEnumId="GEOT_CITY" geoNameLocal="滁州市"/>
    <moqui.basic.Geo geoId="CHN_34_11" geoTypeEnumId="GEOT_CITY" geoNameLocal="阜阳市"/>
    <moqui.basic.Geo geoId="CHN_34_12" geoTypeEnumId="GEOT_CITY" geoNameLocal="宿州市"/>
    <moqui.basic.Geo geoId="CHN_34_13" geoTypeEnumId="GEOT_CITY" geoNameLocal="巢湖市"/>
    <moqui.basic.Geo geoId="CHN_34_14" geoTypeEnumId="GEOT_CITY" geoNameLocal="六安市"/>
    <moqui.basic.Geo geoId="CHN_34_15" geoTypeEnumId="GEOT_CITY" geoNameLocal="亳州市"/>
    <moqui.basic.Geo geoId="CHN_34_16" geoTypeEnumId="GEOT_CITY" geoNameLocal="池州市"/>
    <moqui.basic.Geo geoId="CHN_34_17" geoTypeEnumId="GEOT_CITY" geoNameLocal="宣城市"/>
    <moqui.basic.Geo geoId="CHN_33_1" geoTypeEnumId="GEOT_CITY" geoNameLocal="杭州市"/>
    <moqui.basic.Geo geoId="CHN_33_2" geoTypeEnumId="GEOT_CITY" geoNameLocal="宁波市"/>
    <moqui.basic.Geo geoId="CHN_33_3" geoTypeEnumId="GEOT_CITY" geoNameLocal="温州市"/>
    <moqui.basic.Geo geoId="CHN_33_4" geoTypeEnumId="GEOT_CITY" geoNameLocal="嘉兴市"/>
    <moqui.basic.Geo geoId="CHN_33_5" geoTypeEnumId="GEOT_CITY" geoNameLocal="湖州市"/>
    <moqui.basic.Geo geoId="CHN_33_6" geoTypeEnumId="GEOT_CITY" geoNameLocal="绍兴市"/>
    <moqui.basic.Geo geoId="CHN_33_7" geoTypeEnumId="GEOT_CITY" geoNameLocal="金华市"/>
    <moqui.basic.Geo geoId="CHN_33_8" geoTypeEnumId="GEOT_CITY" geoNameLocal="衢州市"/>
    <moqui.basic.Geo geoId="CHN_33_9" geoTypeEnumId="GEOT_CITY" geoNameLocal="舟山市"/>
    <moqui.basic.Geo geoId="CHN_33_10" geoTypeEnumId="GEOT_CITY" geoNameLocal="台州市"/>
    <moqui.basic.Geo geoId="CHN_33_11" geoTypeEnumId="GEOT_CITY" geoNameLocal="丽水市"/>
    <moqui.basic.Geo geoId="CHN_35_1" geoTypeEnumId="GEOT_CITY" geoNameLocal="福州市"/>
    <moqui.basic.Geo geoId="CHN_35_2" geoTypeEnumId="GEOT_CITY" geoNameLocal="厦门市"/>
    <moqui.basic.Geo geoId="CHN_35_3" geoTypeEnumId="GEOT_CITY" geoNameLocal="莆田市"/>
    <moqui.basic.Geo geoId="CHN_35_4" geoTypeEnumId="GEOT_CITY" geoNameLocal="三明市"/>
    <moqui.basic.Geo geoId="CHN_35_5" geoTypeEnumId="GEOT_CITY" geoNameLocal="泉州市"/>
    <moqui.basic.Geo geoId="CHN_35_6" geoTypeEnumId="GEOT_CITY" geoNameLocal="漳州市"/>
    <moqui.basic.Geo geoId="CHN_35_7" geoTypeEnumId="GEOT_CITY" geoNameLocal="南平市"/>
    <moqui.basic.Geo geoId="CHN_35_8" geoTypeEnumId="GEOT_CITY" geoNameLocal="龙岩市"/>
    <moqui.basic.Geo geoId="CHN_35_9" geoTypeEnumId="GEOT_CITY" geoNameLocal="宁德市"/>

    <moqui.basic.GeoAssoc geoId="CHN_11" toGeoId="CHN_11_1" geoAssocTypeEnumId="GAT_REGIONS"/>
    <moqui.basic.GeoAssoc geoId="CHN_11" toGeoId="CHN_11_2" geoAssocTypeEnumId="GAT_REGIONS"/>
    <moqui.basic.GeoAssoc geoId="CHN_11" toGeoId="CHN_11_3" geoAssocTypeEnumId="GAT_REGIONS"/>
    <moqui.basic.GeoAssoc geoId="CHN_11" toGeoId="CHN_11_4" geoAssocTypeEnumId="GAT_REGIONS"/>
    <moqui.basic.GeoAssoc geoId="CHN_11" toGeoId="CHN_11_5" geoAssocTypeEnumId="GAT_REGIONS"/>
    <moqui.basic.GeoAssoc geoId="CHN_11" toGeoId="CHN_11_6" geoAssocTypeEnumId="GAT_REGIONS"/>
    <moqui.basic.GeoAssoc geoId="CHN_11" toGeoId="CHN_11_7" geoAssocTypeEnumId="GAT_REGIONS"/>
    <moqui.basic.GeoAssoc geoId="CHN_11" toGeoId="CHN_11_8" geoAssocTypeEnumId="GAT_REGIONS"/>
    <moqui.basic.GeoAssoc geoId="CHN_11" toGeoId="CHN_11_9" geoAssocTypeEnumId="GAT_REGIONS"/>
    <moqui.basic.GeoAssoc geoId="CHN_11" toGeoId="CHN_11_10" geoAssocTypeEnumId="GAT_REGIONS"/>
    <moqui.basic.GeoAssoc geoId="CHN_11" toGeoId="CHN_11_11" geoAssocTypeEnumId="GAT_REGIONS"/>
    <moqui.basic.GeoAssoc geoId="CHN_11" toGeoId="CHN_11_12" geoAssocTypeEnumId="GAT_REGIONS"/>
    <moqui.basic.GeoAssoc geoId="CHN_11" toGeoId="CHN_11_13" geoAssocTypeEnumId="GAT_REGIONS"/>
    <moqui.basic.GeoAssoc geoId="CHN_11" toGeoId="CHN_11_14" geoAssocTypeEnumId="GAT_REGIONS"/>
    <moqui.basic.GeoAssoc geoId="CHN_11" toGeoId="CHN_11_15" geoAssocTypeEnumId="GAT_REGIONS"/>
    <moqui.basic.GeoAssoc geoId="CHN_11" toGeoId="CHN_11_16" geoAssocTypeEnumId="GAT_REGIONS"/>
    <moqui.basic.GeoAssoc geoId="CHN_11" toGeoId="CHN_11_17" geoAssocTypeEnumId="GAT_REGIONS"/>
    <moqui.basic.GeoAssoc geoId="CHN_11" toGeoId="CHN_11_18" geoAssocTypeEnumId="GAT_REGIONS"/>
    <moqui.basic.GeoAssoc geoId="CHN_31" toGeoId="CHN_31_1" geoAssocTypeEnumId="GAT_REGIONS"/>
    <moqui.basic.GeoAssoc geoId="CHN_31" toGeoId="CHN_31_2" geoAssocTypeEnumId="GAT_REGIONS"/>
    <moqui.basic.GeoAssoc geoId="CHN_31" toGeoId="CHN_31_3" geoAssocTypeEnumId="GAT_REGIONS"/>
    <moqui.basic.GeoAssoc geoId="CHN_31" toGeoId="CHN_31_4" geoAssocTypeEnumId="GAT_REGIONS"/>
    <moqui.basic.GeoAssoc geoId="CHN_31" toGeoId="CHN_31_5" geoAssocTypeEnumId="GAT_REGIONS"/>
    <moqui.basic.GeoAssoc geoId="CHN_31" toGeoId="CHN_31_6" geoAssocTypeEnumId="GAT_REGIONS"/>
    <moqui.basic.GeoAssoc geoId="CHN_31" toGeoId="CHN_31_7" geoAssocTypeEnumId="GAT_REGIONS"/>
    <moqui.basic.GeoAssoc geoId="CHN_31" toGeoId="CHN_31_8" geoAssocTypeEnumId="GAT_REGIONS"/>
    <moqui.basic.GeoAssoc geoId="CHN_31" toGeoId="CHN_31_9" geoAssocTypeEnumId="GAT_REGIONS"/>
    <moqui.basic.GeoAssoc geoId="CHN_31" toGeoId="CHN_31_10" geoAssocTypeEnumId="GAT_REGIONS"/>
    <moqui.basic.GeoAssoc geoId="CHN_31" toGeoId="CHN_31_11" geoAssocTypeEnumId="GAT_REGIONS"/>
    <moqui.basic.GeoAssoc geoId="CHN_31" toGeoId="CHN_31_12" geoAssocTypeEnumId="GAT_REGIONS"/>
    <moqui.basic.GeoAssoc geoId="CHN_31" toGeoId="CHN_31_13" geoAssocTypeEnumId="GAT_REGIONS"/>
    <moqui.basic.GeoAssoc geoId="CHN_31" toGeoId="CHN_31_14" geoAssocTypeEnumId="GAT_REGIONS"/>
    <moqui.basic.GeoAssoc geoId="CHN_31" toGeoId="CHN_31_15" geoAssocTypeEnumId="GAT_REGIONS"/>
    <moqui.basic.GeoAssoc geoId="CHN_31" toGeoId="CHN_31_16" geoAssocTypeEnumId="GAT_REGIONS"/>
    <moqui.basic.GeoAssoc geoId="CHN_31" toGeoId="CHN_31_17" geoAssocTypeEnumId="GAT_REGIONS"/>
    <moqui.basic.GeoAssoc geoId="CHN_31" toGeoId="CHN_31_18" geoAssocTypeEnumId="GAT_REGIONS"/>
    <moqui.basic.GeoAssoc geoId="CHN_31" toGeoId="CHN_31_19" geoAssocTypeEnumId="GAT_REGIONS"/>
    <moqui.basic.GeoAssoc geoId="CHN_12" toGeoId="CHN_12_1" geoAssocTypeEnumId="GAT_REGIONS"/>
    <moqui.basic.GeoAssoc geoId="CHN_12" toGeoId="CHN_12_2" geoAssocTypeEnumId="GAT_REGIONS"/>
    <moqui.basic.GeoAssoc geoId="CHN_12" toGeoId="CHN_12_3" geoAssocTypeEnumId="GAT_REGIONS"/>
    <moqui.basic.GeoAssoc geoId="CHN_12" toGeoId="CHN_12_4" geoAssocTypeEnumId="GAT_REGIONS"/>
    <moqui.basic.GeoAssoc geoId="CHN_12" toGeoId="CHN_12_5" geoAssocTypeEnumId="GAT_REGIONS"/>
    <moqui.basic.GeoAssoc geoId="CHN_12" toGeoId="CHN_12_6" geoAssocTypeEnumId="GAT_REGIONS"/>
    <moqui.basic.GeoAssoc geoId="CHN_12" toGeoId="CHN_12_7" geoAssocTypeEnumId="GAT_REGIONS"/>
    <moqui.basic.GeoAssoc geoId="CHN_12" toGeoId="CHN_12_8" geoAssocTypeEnumId="GAT_REGIONS"/>
    <moqui.basic.GeoAssoc geoId="CHN_12" toGeoId="CHN_12_9" geoAssocTypeEnumId="GAT_REGIONS"/>
    <moqui.basic.GeoAssoc geoId="CHN_12" toGeoId="CHN_12_10" geoAssocTypeEnumId="GAT_REGIONS"/>
    <moqui.basic.GeoAssoc geoId="CHN_12" toGeoId="CHN_12_11" geoAssocTypeEnumId="GAT_REGIONS"/>
    <moqui.basic.GeoAssoc geoId="CHN_12" toGeoId="CHN_12_12" geoAssocTypeEnumId="GAT_REGIONS"/>
    <moqui.basic.GeoAssoc geoId="CHN_12" toGeoId="CHN_12_13" geoAssocTypeEnumId="GAT_REGIONS"/>
    <moqui.basic.GeoAssoc geoId="CHN_12" toGeoId="CHN_12_14" geoAssocTypeEnumId="GAT_REGIONS"/>
    <moqui.basic.GeoAssoc geoId="CHN_12" toGeoId="CHN_12_15" geoAssocTypeEnumId="GAT_REGIONS"/>
    <moqui.basic.GeoAssoc geoId="CHN_12" toGeoId="CHN_12_16" geoAssocTypeEnumId="GAT_REGIONS"/>
    <moqui.basic.GeoAssoc geoId="CHN_12" toGeoId="CHN_12_17" geoAssocTypeEnumId="GAT_REGIONS"/>
    <moqui.basic.GeoAssoc geoId="CHN_12" toGeoId="CHN_12_18" geoAssocTypeEnumId="GAT_REGIONS"/>
    <moqui.basic.GeoAssoc geoId="CHN_50" toGeoId="CHN_50_1" geoAssocTypeEnumId="GAT_REGIONS"/>
    <moqui.basic.GeoAssoc geoId="CHN_50" toGeoId="CHN_50_2" geoAssocTypeEnumId="GAT_REGIONS"/>
    <moqui.basic.GeoAssoc geoId="CHN_50" toGeoId="CHN_50_3" geoAssocTypeEnumId="GAT_REGIONS"/>
    <moqui.basic.GeoAssoc geoId="CHN_50" toGeoId="CHN_50_4" geoAssocTypeEnumId="GAT_REGIONS"/>
    <moqui.basic.GeoAssoc geoId="CHN_50" toGeoId="CHN_50_5" geoAssocTypeEnumId="GAT_REGIONS"/>
    <moqui.basic.GeoAssoc geoId="CHN_50" toGeoId="CHN_50_6" geoAssocTypeEnumId="GAT_REGIONS"/>
    <moqui.basic.GeoAssoc geoId="CHN_50" toGeoId="CHN_50_7" geoAssocTypeEnumId="GAT_REGIONS"/>
    <moqui.basic.GeoAssoc geoId="CHN_50" toGeoId="CHN_50_8" geoAssocTypeEnumId="GAT_REGIONS"/>
    <moqui.basic.GeoAssoc geoId="CHN_50" toGeoId="CHN_50_9" geoAssocTypeEnumId="GAT_REGIONS"/>
    <moqui.basic.GeoAssoc geoId="CHN_50" toGeoId="CHN_50_10" geoAssocTypeEnumId="GAT_REGIONS"/>
    <moqui.basic.GeoAssoc geoId="CHN_50" toGeoId="CHN_50_11" geoAssocTypeEnumId="GAT_REGIONS"/>
    <moqui.basic.GeoAssoc geoId="CHN_50" toGeoId="CHN_50_12" geoAssocTypeEnumId="GAT_REGIONS"/>
    <moqui.basic.GeoAssoc geoId="CHN_50" toGeoId="CHN_50_13" geoAssocTypeEnumId="GAT_REGIONS"/>
    <moqui.basic.GeoAssoc geoId="CHN_50" toGeoId="CHN_50_14" geoAssocTypeEnumId="GAT_REGIONS"/>
    <moqui.basic.GeoAssoc geoId="CHN_50" toGeoId="CHN_50_15" geoAssocTypeEnumId="GAT_REGIONS"/>
    <moqui.basic.GeoAssoc geoId="CHN_50" toGeoId="CHN_50_16" geoAssocTypeEnumId="GAT_REGIONS"/>
    <moqui.basic.GeoAssoc geoId="CHN_50" toGeoId="CHN_50_17" geoAssocTypeEnumId="GAT_REGIONS"/>
    <moqui.basic.GeoAssoc geoId="CHN_50" toGeoId="CHN_50_18" geoAssocTypeEnumId="GAT_REGIONS"/>
    <moqui.basic.GeoAssoc geoId="CHN_50" toGeoId="CHN_50_19" geoAssocTypeEnumId="GAT_REGIONS"/>
    <moqui.basic.GeoAssoc geoId="CHN_50" toGeoId="CHN_50_20" geoAssocTypeEnumId="GAT_REGIONS"/>
    <moqui.basic.GeoAssoc geoId="CHN_50" toGeoId="CHN_50_21" geoAssocTypeEnumId="GAT_REGIONS"/>
    <moqui.basic.GeoAssoc geoId="CHN_50" toGeoId="CHN_50_22" geoAssocTypeEnumId="GAT_REGIONS"/>
    <moqui.basic.GeoAssoc geoId="CHN_50" toGeoId="CHN_50_23" geoAssocTypeEnumId="GAT_REGIONS"/>
    <moqui.basic.GeoAssoc geoId="CHN_50" toGeoId="CHN_50_24" geoAssocTypeEnumId="GAT_REGIONS"/>
    <moqui.basic.GeoAssoc geoId="CHN_50" toGeoId="CHN_50_25" geoAssocTypeEnumId="GAT_REGIONS"/>
    <moqui.basic.GeoAssoc geoId="CHN_50" toGeoId="CHN_50_26" geoAssocTypeEnumId="GAT_REGIONS"/>
    <moqui.basic.GeoAssoc geoId="CHN_50" toGeoId="CHN_50_27" geoAssocTypeEnumId="GAT_REGIONS"/>
    <moqui.basic.GeoAssoc geoId="CHN_50" toGeoId="CHN_50_28" geoAssocTypeEnumId="GAT_REGIONS"/>
    <moqui.basic.GeoAssoc geoId="CHN_50" toGeoId="CHN_50_29" geoAssocTypeEnumId="GAT_REGIONS"/>
    <moqui.basic.GeoAssoc geoId="CHN_50" toGeoId="CHN_50_30" geoAssocTypeEnumId="GAT_REGIONS"/>
    <moqui.basic.GeoAssoc geoId="CHN_50" toGeoId="CHN_50_31" geoAssocTypeEnumId="GAT_REGIONS"/>
    <moqui.basic.GeoAssoc geoId="CHN_50" toGeoId="CHN_50_32" geoAssocTypeEnumId="GAT_REGIONS"/>
    <moqui.basic.GeoAssoc geoId="CHN_50" toGeoId="CHN_50_33" geoAssocTypeEnumId="GAT_REGIONS"/>
    <moqui.basic.GeoAssoc geoId="CHN_50" toGeoId="CHN_50_34" geoAssocTypeEnumId="GAT_REGIONS"/>
    <moqui.basic.GeoAssoc geoId="CHN_50" toGeoId="CHN_50_35" geoAssocTypeEnumId="GAT_REGIONS"/>
    <moqui.basic.GeoAssoc geoId="CHN_50" toGeoId="CHN_50_36" geoAssocTypeEnumId="GAT_REGIONS"/>
    <moqui.basic.GeoAssoc geoId="CHN_50" toGeoId="CHN_50_37" geoAssocTypeEnumId="GAT_REGIONS"/>
    <moqui.basic.GeoAssoc geoId="CHN_50" toGeoId="CHN_50_38" geoAssocTypeEnumId="GAT_REGIONS"/>
    <moqui.basic.GeoAssoc geoId="CHN_50" toGeoId="CHN_50_39" geoAssocTypeEnumId="GAT_REGIONS"/>
    <moqui.basic.GeoAssoc geoId="CHN_50" toGeoId="CHN_50_40" geoAssocTypeEnumId="GAT_REGIONS"/>
    <moqui.basic.GeoAssoc geoId="CHN_23" toGeoId="CHN_23_1" geoAssocTypeEnumId="GAT_REGIONS"/>
    <moqui.basic.GeoAssoc geoId="CHN_23" toGeoId="CHN_23_2" geoAssocTypeEnumId="GAT_REGIONS"/>
    <moqui.basic.GeoAssoc geoId="CHN_23" toGeoId="CHN_23_3" geoAssocTypeEnumId="GAT_REGIONS"/>
    <moqui.basic.GeoAssoc geoId="CHN_23" toGeoId="CHN_23_4" geoAssocTypeEnumId="GAT_REGIONS"/>
    <moqui.basic.GeoAssoc geoId="CHN_23" toGeoId="CHN_23_5" geoAssocTypeEnumId="GAT_REGIONS"/>
    <moqui.basic.GeoAssoc geoId="CHN_23" toGeoId="CHN_23_6" geoAssocTypeEnumId="GAT_REGIONS"/>
    <moqui.basic.GeoAssoc geoId="CHN_23" toGeoId="CHN_23_7" geoAssocTypeEnumId="GAT_REGIONS"/>
    <moqui.basic.GeoAssoc geoId="CHN_23" toGeoId="CHN_23_8" geoAssocTypeEnumId="GAT_REGIONS"/>
    <moqui.basic.GeoAssoc geoId="CHN_23" toGeoId="CHN_23_9" geoAssocTypeEnumId="GAT_REGIONS"/>
    <moqui.basic.GeoAssoc geoId="CHN_23" toGeoId="CHN_23_10" geoAssocTypeEnumId="GAT_REGIONS"/>
    <moqui.basic.GeoAssoc geoId="CHN_23" toGeoId="CHN_23_11" geoAssocTypeEnumId="GAT_REGIONS"/>
    <moqui.basic.GeoAssoc geoId="CHN_23" toGeoId="CHN_23_12" geoAssocTypeEnumId="GAT_REGIONS"/>
    <moqui.basic.GeoAssoc geoId="CHN_23" toGeoId="CHN_23_13" geoAssocTypeEnumId="GAT_REGIONS"/>
    <moqui.basic.GeoAssoc geoId="CHN_22" toGeoId="CHN_22_1" geoAssocTypeEnumId="GAT_REGIONS"/>
    <moqui.basic.GeoAssoc geoId="CHN_22" toGeoId="CHN_22_2" geoAssocTypeEnumId="GAT_REGIONS"/>
    <moqui.basic.GeoAssoc geoId="CHN_22" toGeoId="CHN_22_3" geoAssocTypeEnumId="GAT_REGIONS"/>
    <moqui.basic.GeoAssoc geoId="CHN_22" toGeoId="CHN_22_4" geoAssocTypeEnumId="GAT_REGIONS"/>
    <moqui.basic.GeoAssoc geoId="CHN_22" toGeoId="CHN_22_5" geoAssocTypeEnumId="GAT_REGIONS"/>
    <moqui.basic.GeoAssoc geoId="CHN_22" toGeoId="CHN_22_6" geoAssocTypeEnumId="GAT_REGIONS"/>
    <moqui.basic.GeoAssoc geoId="CHN_22" toGeoId="CHN_22_7" geoAssocTypeEnumId="GAT_REGIONS"/>
    <moqui.basic.GeoAssoc geoId="CHN_22" toGeoId="CHN_22_8" geoAssocTypeEnumId="GAT_REGIONS"/>
    <moqui.basic.GeoAssoc geoId="CHN_22" toGeoId="CHN_22_9" geoAssocTypeEnumId="GAT_REGIONS"/>
    <moqui.basic.GeoAssoc geoId="CHN_21" toGeoId="CHN_21_1" geoAssocTypeEnumId="GAT_REGIONS"/>
    <moqui.basic.GeoAssoc geoId="CHN_21" toGeoId="CHN_21_2" geoAssocTypeEnumId="GAT_REGIONS"/>
    <moqui.basic.GeoAssoc geoId="CHN_21" toGeoId="CHN_21_3" geoAssocTypeEnumId="GAT_REGIONS"/>
    <moqui.basic.GeoAssoc geoId="CHN_21" toGeoId="CHN_21_4" geoAssocTypeEnumId="GAT_REGIONS"/>
    <moqui.basic.GeoAssoc geoId="CHN_21" toGeoId="CHN_21_5" geoAssocTypeEnumId="GAT_REGIONS"/>
    <moqui.basic.GeoAssoc geoId="CHN_21" toGeoId="CHN_21_6" geoAssocTypeEnumId="GAT_REGIONS"/>
    <moqui.basic.GeoAssoc geoId="CHN_21" toGeoId="CHN_21_7" geoAssocTypeEnumId="GAT_REGIONS"/>
    <moqui.basic.GeoAssoc geoId="CHN_21" toGeoId="CHN_21_8" geoAssocTypeEnumId="GAT_REGIONS"/>
    <moqui.basic.GeoAssoc geoId="CHN_21" toGeoId="CHN_21_9" geoAssocTypeEnumId="GAT_REGIONS"/>
    <moqui.basic.GeoAssoc geoId="CHN_21" toGeoId="CHN_21_10" geoAssocTypeEnumId="GAT_REGIONS"/>
    <moqui.basic.GeoAssoc geoId="CHN_21" toGeoId="CHN_21_11" geoAssocTypeEnumId="GAT_REGIONS"/>
    <moqui.basic.GeoAssoc geoId="CHN_21" toGeoId="CHN_21_12" geoAssocTypeEnumId="GAT_REGIONS"/>
    <moqui.basic.GeoAssoc geoId="CHN_21" toGeoId="CHN_21_13" geoAssocTypeEnumId="GAT_REGIONS"/>
    <moqui.basic.GeoAssoc geoId="CHN_21" toGeoId="CHN_21_14" geoAssocTypeEnumId="GAT_REGIONS"/>
    <moqui.basic.GeoAssoc geoId="CHN_37" toGeoId="CHN_37_1" geoAssocTypeEnumId="GAT_REGIONS"/>
    <moqui.basic.GeoAssoc geoId="CHN_37" toGeoId="CHN_37_2" geoAssocTypeEnumId="GAT_REGIONS"/>
    <moqui.basic.GeoAssoc geoId="CHN_37" toGeoId="CHN_37_3" geoAssocTypeEnumId="GAT_REGIONS"/>
    <moqui.basic.GeoAssoc geoId="CHN_37" toGeoId="CHN_37_4" geoAssocTypeEnumId="GAT_REGIONS"/>
    <moqui.basic.GeoAssoc geoId="CHN_37" toGeoId="CHN_37_5" geoAssocTypeEnumId="GAT_REGIONS"/>
    <moqui.basic.GeoAssoc geoId="CHN_37" toGeoId="CHN_37_6" geoAssocTypeEnumId="GAT_REGIONS"/>
    <moqui.basic.GeoAssoc geoId="CHN_37" toGeoId="CHN_37_7" geoAssocTypeEnumId="GAT_REGIONS"/>
    <moqui.basic.GeoAssoc geoId="CHN_37" toGeoId="CHN_37_8" geoAssocTypeEnumId="GAT_REGIONS"/>
    <moqui.basic.GeoAssoc geoId="CHN_37" toGeoId="CHN_37_9" geoAssocTypeEnumId="GAT_REGIONS"/>
    <moqui.basic.GeoAssoc geoId="CHN_37" toGeoId="CHN_37_10" geoAssocTypeEnumId="GAT_REGIONS"/>
    <moqui.basic.GeoAssoc geoId="CHN_37" toGeoId="CHN_37_11" geoAssocTypeEnumId="GAT_REGIONS"/>
    <moqui.basic.GeoAssoc geoId="CHN_37" toGeoId="CHN_37_12" geoAssocTypeEnumId="GAT_REGIONS"/>
    <moqui.basic.GeoAssoc geoId="CHN_37" toGeoId="CHN_37_13" geoAssocTypeEnumId="GAT_REGIONS"/>
    <moqui.basic.GeoAssoc geoId="CHN_37" toGeoId="CHN_37_14" geoAssocTypeEnumId="GAT_REGIONS"/>
    <moqui.basic.GeoAssoc geoId="CHN_37" toGeoId="CHN_37_15" geoAssocTypeEnumId="GAT_REGIONS"/>
    <moqui.basic.GeoAssoc geoId="CHN_37" toGeoId="CHN_37_16" geoAssocTypeEnumId="GAT_REGIONS"/>
    <moqui.basic.GeoAssoc geoId="CHN_37" toGeoId="CHN_37_17" geoAssocTypeEnumId="GAT_REGIONS"/>
    <moqui.basic.GeoAssoc geoId="CHN_14" toGeoId="CHN_14_1" geoAssocTypeEnumId="GAT_REGIONS"/>
    <moqui.basic.GeoAssoc geoId="CHN_14" toGeoId="CHN_14_2" geoAssocTypeEnumId="GAT_REGIONS"/>
    <moqui.basic.GeoAssoc geoId="CHN_14" toGeoId="CHN_14_3" geoAssocTypeEnumId="GAT_REGIONS"/>
    <moqui.basic.GeoAssoc geoId="CHN_14" toGeoId="CHN_14_4" geoAssocTypeEnumId="GAT_REGIONS"/>
    <moqui.basic.GeoAssoc geoId="CHN_14" toGeoId="CHN_14_5" geoAssocTypeEnumId="GAT_REGIONS"/>
    <moqui.basic.GeoAssoc geoId="CHN_14" toGeoId="CHN_14_6" geoAssocTypeEnumId="GAT_REGIONS"/>
    <moqui.basic.GeoAssoc geoId="CHN_14" toGeoId="CHN_14_7" geoAssocTypeEnumId="GAT_REGIONS"/>
    <moqui.basic.GeoAssoc geoId="CHN_14" toGeoId="CHN_14_8" geoAssocTypeEnumId="GAT_REGIONS"/>
    <moqui.basic.GeoAssoc geoId="CHN_14" toGeoId="CHN_14_9" geoAssocTypeEnumId="GAT_REGIONS"/>
    <moqui.basic.GeoAssoc geoId="CHN_14" toGeoId="CHN_14_10" geoAssocTypeEnumId="GAT_REGIONS"/>
    <moqui.basic.GeoAssoc geoId="CHN_14" toGeoId="CHN_14_11" geoAssocTypeEnumId="GAT_REGIONS"/>
    <moqui.basic.GeoAssoc geoId="CHN_61" toGeoId="CHN_61_1" geoAssocTypeEnumId="GAT_REGIONS"/>
    <moqui.basic.GeoAssoc geoId="CHN_61" toGeoId="CHN_61_2" geoAssocTypeEnumId="GAT_REGIONS"/>
    <moqui.basic.GeoAssoc geoId="CHN_61" toGeoId="CHN_61_3" geoAssocTypeEnumId="GAT_REGIONS"/>
    <moqui.basic.GeoAssoc geoId="CHN_61" toGeoId="CHN_61_4" geoAssocTypeEnumId="GAT_REGIONS"/>
    <moqui.basic.GeoAssoc geoId="CHN_61" toGeoId="CHN_61_5" geoAssocTypeEnumId="GAT_REGIONS"/>
    <moqui.basic.GeoAssoc geoId="CHN_61" toGeoId="CHN_61_6" geoAssocTypeEnumId="GAT_REGIONS"/>
    <moqui.basic.GeoAssoc geoId="CHN_61" toGeoId="CHN_61_7" geoAssocTypeEnumId="GAT_REGIONS"/>
    <moqui.basic.GeoAssoc geoId="CHN_61" toGeoId="CHN_61_8" geoAssocTypeEnumId="GAT_REGIONS"/>
    <moqui.basic.GeoAssoc geoId="CHN_61" toGeoId="CHN_61_9" geoAssocTypeEnumId="GAT_REGIONS"/>
    <moqui.basic.GeoAssoc geoId="CHN_61" toGeoId="CHN_61_10" geoAssocTypeEnumId="GAT_REGIONS"/>
    <moqui.basic.GeoAssoc geoId="CHN_13" toGeoId="CHN_13_1" geoAssocTypeEnumId="GAT_REGIONS"/>
    <moqui.basic.GeoAssoc geoId="CHN_13" toGeoId="CHN_13_2" geoAssocTypeEnumId="GAT_REGIONS"/>
    <moqui.basic.GeoAssoc geoId="CHN_13" toGeoId="CHN_13_3" geoAssocTypeEnumId="GAT_REGIONS"/>
    <moqui.basic.GeoAssoc geoId="CHN_13" toGeoId="CHN_13_4" geoAssocTypeEnumId="GAT_REGIONS"/>
    <moqui.basic.GeoAssoc geoId="CHN_13" toGeoId="CHN_13_5" geoAssocTypeEnumId="GAT_REGIONS"/>
    <moqui.basic.GeoAssoc geoId="CHN_13" toGeoId="CHN_13_6" geoAssocTypeEnumId="GAT_REGIONS"/>
    <moqui.basic.GeoAssoc geoId="CHN_13" toGeoId="CHN_13_7" geoAssocTypeEnumId="GAT_REGIONS"/>
    <moqui.basic.GeoAssoc geoId="CHN_13" toGeoId="CHN_13_8" geoAssocTypeEnumId="GAT_REGIONS"/>
    <moqui.basic.GeoAssoc geoId="CHN_13" toGeoId="CHN_13_9" geoAssocTypeEnumId="GAT_REGIONS"/>
    <moqui.basic.GeoAssoc geoId="CHN_13" toGeoId="CHN_13_10" geoAssocTypeEnumId="GAT_REGIONS"/>
    <moqui.basic.GeoAssoc geoId="CHN_13" toGeoId="CHN_13_11" geoAssocTypeEnumId="GAT_REGIONS"/>
    <moqui.basic.GeoAssoc geoId="CHN_41" toGeoId="CHN_41_1" geoAssocTypeEnumId="GAT_REGIONS"/>
    <moqui.basic.GeoAssoc geoId="CHN_41" toGeoId="CHN_41_2" geoAssocTypeEnumId="GAT_REGIONS"/>
    <moqui.basic.GeoAssoc geoId="CHN_41" toGeoId="CHN_41_3" geoAssocTypeEnumId="GAT_REGIONS"/>
    <moqui.basic.GeoAssoc geoId="CHN_41" toGeoId="CHN_41_4" geoAssocTypeEnumId="GAT_REGIONS"/>
    <moqui.basic.GeoAssoc geoId="CHN_41" toGeoId="CHN_41_5" geoAssocTypeEnumId="GAT_REGIONS"/>
    <moqui.basic.GeoAssoc geoId="CHN_41" toGeoId="CHN_41_6" geoAssocTypeEnumId="GAT_REGIONS"/>
    <moqui.basic.GeoAssoc geoId="CHN_41" toGeoId="CHN_41_7" geoAssocTypeEnumId="GAT_REGIONS"/>
    <moqui.basic.GeoAssoc geoId="CHN_41" toGeoId="CHN_41_8" geoAssocTypeEnumId="GAT_REGIONS"/>
    <moqui.basic.GeoAssoc geoId="CHN_41" toGeoId="CHN_41_9" geoAssocTypeEnumId="GAT_REGIONS"/>
    <moqui.basic.GeoAssoc geoId="CHN_41" toGeoId="CHN_41_10" geoAssocTypeEnumId="GAT_REGIONS"/>
    <moqui.basic.GeoAssoc geoId="CHN_41" toGeoId="CHN_41_11" geoAssocTypeEnumId="GAT_REGIONS"/>
    <moqui.basic.GeoAssoc geoId="CHN_41" toGeoId="CHN_41_12" geoAssocTypeEnumId="GAT_REGIONS"/>
    <moqui.basic.GeoAssoc geoId="CHN_41" toGeoId="CHN_41_13" geoAssocTypeEnumId="GAT_REGIONS"/>
    <moqui.basic.GeoAssoc geoId="CHN_41" toGeoId="CHN_41_14" geoAssocTypeEnumId="GAT_REGIONS"/>
    <moqui.basic.GeoAssoc geoId="CHN_41" toGeoId="CHN_41_15" geoAssocTypeEnumId="GAT_REGIONS"/>
    <moqui.basic.GeoAssoc geoId="CHN_41" toGeoId="CHN_41_16" geoAssocTypeEnumId="GAT_REGIONS"/>
    <moqui.basic.GeoAssoc geoId="CHN_41" toGeoId="CHN_41_17" geoAssocTypeEnumId="GAT_REGIONS"/>
    <moqui.basic.GeoAssoc geoId="CHN_41" toGeoId="CHN_41_18" geoAssocTypeEnumId="GAT_REGIONS"/>
    <moqui.basic.GeoAssoc geoId="CHN_42" toGeoId="CHN_42_1" geoAssocTypeEnumId="GAT_REGIONS"/>
    <moqui.basic.GeoAssoc geoId="CHN_42" toGeoId="CHN_42_2" geoAssocTypeEnumId="GAT_REGIONS"/>
    <moqui.basic.GeoAssoc geoId="CHN_42" toGeoId="CHN_42_3" geoAssocTypeEnumId="GAT_REGIONS"/>
    <moqui.basic.GeoAssoc geoId="CHN_42" toGeoId="CHN_42_4" geoAssocTypeEnumId="GAT_REGIONS"/>
    <moqui.basic.GeoAssoc geoId="CHN_42" toGeoId="CHN_42_5" geoAssocTypeEnumId="GAT_REGIONS"/>
    <moqui.basic.GeoAssoc geoId="CHN_42" toGeoId="CHN_42_6" geoAssocTypeEnumId="GAT_REGIONS"/>
    <moqui.basic.GeoAssoc geoId="CHN_42" toGeoId="CHN_42_7" geoAssocTypeEnumId="GAT_REGIONS"/>
    <moqui.basic.GeoAssoc geoId="CHN_42" toGeoId="CHN_42_8" geoAssocTypeEnumId="GAT_REGIONS"/>
    <moqui.basic.GeoAssoc geoId="CHN_42" toGeoId="CHN_42_9" geoAssocTypeEnumId="GAT_REGIONS"/>
    <moqui.basic.GeoAssoc geoId="CHN_42" toGeoId="CHN_42_10" geoAssocTypeEnumId="GAT_REGIONS"/>
    <moqui.basic.GeoAssoc geoId="CHN_42" toGeoId="CHN_42_11" geoAssocTypeEnumId="GAT_REGIONS"/>
    <moqui.basic.GeoAssoc geoId="CHN_42" toGeoId="CHN_42_12" geoAssocTypeEnumId="GAT_REGIONS"/>
    <moqui.basic.GeoAssoc geoId="CHN_42" toGeoId="CHN_42_13" geoAssocTypeEnumId="GAT_REGIONS"/>
    <moqui.basic.GeoAssoc geoId="CHN_42" toGeoId="CHN_42_14" geoAssocTypeEnumId="GAT_REGIONS"/>
    <moqui.basic.GeoAssoc geoId="CHN_42" toGeoId="CHN_42_15" geoAssocTypeEnumId="GAT_REGIONS"/>
    <moqui.basic.GeoAssoc geoId="CHN_42" toGeoId="CHN_42_16" geoAssocTypeEnumId="GAT_REGIONS"/>
    <moqui.basic.GeoAssoc geoId="CHN_42" toGeoId="CHN_42_17" geoAssocTypeEnumId="GAT_REGIONS"/>
    <moqui.basic.GeoAssoc geoId="CHN_43" toGeoId="CHN_43_1" geoAssocTypeEnumId="GAT_REGIONS"/>
    <moqui.basic.GeoAssoc geoId="CHN_43" toGeoId="CHN_43_2" geoAssocTypeEnumId="GAT_REGIONS"/>
    <moqui.basic.GeoAssoc geoId="CHN_43" toGeoId="CHN_43_3" geoAssocTypeEnumId="GAT_REGIONS"/>
    <moqui.basic.GeoAssoc geoId="CHN_43" toGeoId="CHN_43_4" geoAssocTypeEnumId="GAT_REGIONS"/>
    <moqui.basic.GeoAssoc geoId="CHN_43" toGeoId="CHN_43_5" geoAssocTypeEnumId="GAT_REGIONS"/>
    <moqui.basic.GeoAssoc geoId="CHN_43" toGeoId="CHN_43_6" geoAssocTypeEnumId="GAT_REGIONS"/>
    <moqui.basic.GeoAssoc geoId="CHN_43" toGeoId="CHN_43_7" geoAssocTypeEnumId="GAT_REGIONS"/>
    <moqui.basic.GeoAssoc geoId="CHN_43" toGeoId="CHN_43_8" geoAssocTypeEnumId="GAT_REGIONS"/>
    <moqui.basic.GeoAssoc geoId="CHN_43" toGeoId="CHN_43_9" geoAssocTypeEnumId="GAT_REGIONS"/>
    <moqui.basic.GeoAssoc geoId="CHN_43" toGeoId="CHN_43_10" geoAssocTypeEnumId="GAT_REGIONS"/>
    <moqui.basic.GeoAssoc geoId="CHN_43" toGeoId="CHN_43_11" geoAssocTypeEnumId="GAT_REGIONS"/>
    <moqui.basic.GeoAssoc geoId="CHN_43" toGeoId="CHN_43_12" geoAssocTypeEnumId="GAT_REGIONS"/>
    <moqui.basic.GeoAssoc geoId="CHN_43" toGeoId="CHN_43_13" geoAssocTypeEnumId="GAT_REGIONS"/>
    <moqui.basic.GeoAssoc geoId="CHN_43" toGeoId="CHN_43_14" geoAssocTypeEnumId="GAT_REGIONS"/>
    <moqui.basic.GeoAssoc geoId="CHN_46" toGeoId="CHN_46_1" geoAssocTypeEnumId="GAT_REGIONS"/>
    <moqui.basic.GeoAssoc geoId="CHN_46" toGeoId="CHN_46_2" geoAssocTypeEnumId="GAT_REGIONS"/>
    <moqui.basic.GeoAssoc geoId="CHN_46" toGeoId="CHN_46_3" geoAssocTypeEnumId="GAT_REGIONS"/>
    <moqui.basic.GeoAssoc geoId="CHN_46" toGeoId="CHN_46_4" geoAssocTypeEnumId="GAT_REGIONS"/>
    <moqui.basic.GeoAssoc geoId="CHN_46" toGeoId="CHN_46_5" geoAssocTypeEnumId="GAT_REGIONS"/>
    <moqui.basic.GeoAssoc geoId="CHN_46" toGeoId="CHN_46_6" geoAssocTypeEnumId="GAT_REGIONS"/>
    <moqui.basic.GeoAssoc geoId="CHN_46" toGeoId="CHN_46_7" geoAssocTypeEnumId="GAT_REGIONS"/>
    <moqui.basic.GeoAssoc geoId="CHN_46" toGeoId="CHN_46_8" geoAssocTypeEnumId="GAT_REGIONS"/>
    <moqui.basic.GeoAssoc geoId="CHN_46" toGeoId="CHN_46_9" geoAssocTypeEnumId="GAT_REGIONS"/>
    <moqui.basic.GeoAssoc geoId="CHN_46" toGeoId="CHN_46_10" geoAssocTypeEnumId="GAT_REGIONS"/>
    <moqui.basic.GeoAssoc geoId="CHN_46" toGeoId="CHN_46_11" geoAssocTypeEnumId="GAT_REGIONS"/>
    <moqui.basic.GeoAssoc geoId="CHN_46" toGeoId="CHN_46_12" geoAssocTypeEnumId="GAT_REGIONS"/>
    <moqui.basic.GeoAssoc geoId="CHN_46" toGeoId="CHN_46_13" geoAssocTypeEnumId="GAT_REGIONS"/>
    <moqui.basic.GeoAssoc geoId="CHN_46" toGeoId="CHN_46_14" geoAssocTypeEnumId="GAT_REGIONS"/>
    <moqui.basic.GeoAssoc geoId="CHN_46" toGeoId="CHN_46_15" geoAssocTypeEnumId="GAT_REGIONS"/>
    <moqui.basic.GeoAssoc geoId="CHN_46" toGeoId="CHN_46_16" geoAssocTypeEnumId="GAT_REGIONS"/>
    <moqui.basic.GeoAssoc geoId="CHN_46" toGeoId="CHN_46_17" geoAssocTypeEnumId="GAT_REGIONS"/>
    <moqui.basic.GeoAssoc geoId="CHN_46" toGeoId="CHN_46_18" geoAssocTypeEnumId="GAT_REGIONS"/>
    <moqui.basic.GeoAssoc geoId="CHN_32" toGeoId="CHN_32_1" geoAssocTypeEnumId="GAT_REGIONS"/>
    <moqui.basic.GeoAssoc geoId="CHN_32" toGeoId="CHN_32_2" geoAssocTypeEnumId="GAT_REGIONS"/>
    <moqui.basic.GeoAssoc geoId="CHN_32" toGeoId="CHN_32_3" geoAssocTypeEnumId="GAT_REGIONS"/>
    <moqui.basic.GeoAssoc geoId="CHN_32" toGeoId="CHN_32_4" geoAssocTypeEnumId="GAT_REGIONS"/>
    <moqui.basic.GeoAssoc geoId="CHN_32" toGeoId="CHN_32_5" geoAssocTypeEnumId="GAT_REGIONS"/>
    <moqui.basic.GeoAssoc geoId="CHN_32" toGeoId="CHN_32_6" geoAssocTypeEnumId="GAT_REGIONS"/>
    <moqui.basic.GeoAssoc geoId="CHN_32" toGeoId="CHN_32_7" geoAssocTypeEnumId="GAT_REGIONS"/>
    <moqui.basic.GeoAssoc geoId="CHN_32" toGeoId="CHN_32_8" geoAssocTypeEnumId="GAT_REGIONS"/>
    <moqui.basic.GeoAssoc geoId="CHN_32" toGeoId="CHN_32_9" geoAssocTypeEnumId="GAT_REGIONS"/>
    <moqui.basic.GeoAssoc geoId="CHN_32" toGeoId="CHN_32_10" geoAssocTypeEnumId="GAT_REGIONS"/>
    <moqui.basic.GeoAssoc geoId="CHN_32" toGeoId="CHN_32_11" geoAssocTypeEnumId="GAT_REGIONS"/>
    <moqui.basic.GeoAssoc geoId="CHN_32" toGeoId="CHN_32_12" geoAssocTypeEnumId="GAT_REGIONS"/>
    <moqui.basic.GeoAssoc geoId="CHN_32" toGeoId="CHN_32_13" geoAssocTypeEnumId="GAT_REGIONS"/>
    <moqui.basic.GeoAssoc geoId="CHN_36" toGeoId="CHN_36_1" geoAssocTypeEnumId="GAT_REGIONS"/>
    <moqui.basic.GeoAssoc geoId="CHN_36" toGeoId="CHN_36_2" geoAssocTypeEnumId="GAT_REGIONS"/>
    <moqui.basic.GeoAssoc geoId="CHN_36" toGeoId="CHN_36_3" geoAssocTypeEnumId="GAT_REGIONS"/>
    <moqui.basic.GeoAssoc geoId="CHN_36" toGeoId="CHN_36_4" geoAssocTypeEnumId="GAT_REGIONS"/>
    <moqui.basic.GeoAssoc geoId="CHN_36" toGeoId="CHN_36_5" geoAssocTypeEnumId="GAT_REGIONS"/>
    <moqui.basic.GeoAssoc geoId="CHN_36" toGeoId="CHN_36_6" geoAssocTypeEnumId="GAT_REGIONS"/>
    <moqui.basic.GeoAssoc geoId="CHN_36" toGeoId="CHN_36_7" geoAssocTypeEnumId="GAT_REGIONS"/>
    <moqui.basic.GeoAssoc geoId="CHN_36" toGeoId="CHN_36_8" geoAssocTypeEnumId="GAT_REGIONS"/>
    <moqui.basic.GeoAssoc geoId="CHN_36" toGeoId="CHN_36_9" geoAssocTypeEnumId="GAT_REGIONS"/>
    <moqui.basic.GeoAssoc geoId="CHN_36" toGeoId="CHN_36_10" geoAssocTypeEnumId="GAT_REGIONS"/>
    <moqui.basic.GeoAssoc geoId="CHN_36" toGeoId="CHN_36_11" geoAssocTypeEnumId="GAT_REGIONS"/>
    <moqui.basic.GeoAssoc geoId="CHN_44" toGeoId="CHN_44_1" geoAssocTypeEnumId="GAT_REGIONS"/>
    <moqui.basic.GeoAssoc geoId="CHN_44" toGeoId="CHN_44_2" geoAssocTypeEnumId="GAT_REGIONS"/>
    <moqui.basic.GeoAssoc geoId="CHN_44" toGeoId="CHN_44_3" geoAssocTypeEnumId="GAT_REGIONS"/>
    <moqui.basic.GeoAssoc geoId="CHN_44" toGeoId="CHN_44_4" geoAssocTypeEnumId="GAT_REGIONS"/>
    <moqui.basic.GeoAssoc geoId="CHN_44" toGeoId="CHN_44_5" geoAssocTypeEnumId="GAT_REGIONS"/>
    <moqui.basic.GeoAssoc geoId="CHN_44" toGeoId="CHN_44_6" geoAssocTypeEnumId="GAT_REGIONS"/>
    <moqui.basic.GeoAssoc geoId="CHN_44" toGeoId="CHN_44_7" geoAssocTypeEnumId="GAT_REGIONS"/>
    <moqui.basic.GeoAssoc geoId="CHN_44" toGeoId="CHN_44_8" geoAssocTypeEnumId="GAT_REGIONS"/>
    <moqui.basic.GeoAssoc geoId="CHN_44" toGeoId="CHN_44_9" geoAssocTypeEnumId="GAT_REGIONS"/>
    <moqui.basic.GeoAssoc geoId="CHN_44" toGeoId="CHN_44_10" geoAssocTypeEnumId="GAT_REGIONS"/>
    <moqui.basic.GeoAssoc geoId="CHN_44" toGeoId="CHN_44_11" geoAssocTypeEnumId="GAT_REGIONS"/>
    <moqui.basic.GeoAssoc geoId="CHN_44" toGeoId="CHN_44_12" geoAssocTypeEnumId="GAT_REGIONS"/>
    <moqui.basic.GeoAssoc geoId="CHN_44" toGeoId="CHN_44_13" geoAssocTypeEnumId="GAT_REGIONS"/>
    <moqui.basic.GeoAssoc geoId="CHN_44" toGeoId="CHN_44_14" geoAssocTypeEnumId="GAT_REGIONS"/>
    <moqui.basic.GeoAssoc geoId="CHN_44" toGeoId="CHN_44_15" geoAssocTypeEnumId="GAT_REGIONS"/>
    <moqui.basic.GeoAssoc geoId="CHN_44" toGeoId="CHN_44_16" geoAssocTypeEnumId="GAT_REGIONS"/>
    <moqui.basic.GeoAssoc geoId="CHN_44" toGeoId="CHN_44_17" geoAssocTypeEnumId="GAT_REGIONS"/>
    <moqui.basic.GeoAssoc geoId="CHN_44" toGeoId="CHN_44_18" geoAssocTypeEnumId="GAT_REGIONS"/>
    <moqui.basic.GeoAssoc geoId="CHN_44" toGeoId="CHN_44_19" geoAssocTypeEnumId="GAT_REGIONS"/>
    <moqui.basic.GeoAssoc geoId="CHN_44" toGeoId="CHN_44_20" geoAssocTypeEnumId="GAT_REGIONS"/>
    <moqui.basic.GeoAssoc geoId="CHN_44" toGeoId="CHN_44_21" geoAssocTypeEnumId="GAT_REGIONS"/>
    <moqui.basic.GeoAssoc geoId="CHN_45" toGeoId="CHN_45_1" geoAssocTypeEnumId="GAT_REGIONS"/>
    <moqui.basic.GeoAssoc geoId="CHN_45" toGeoId="CHN_45_2" geoAssocTypeEnumId="GAT_REGIONS"/>
    <moqui.basic.GeoAssoc geoId="CHN_45" toGeoId="CHN_45_3" geoAssocTypeEnumId="GAT_REGIONS"/>
    <moqui.basic.GeoAssoc geoId="CHN_45" toGeoId="CHN_45_4" geoAssocTypeEnumId="GAT_REGIONS"/>
    <moqui.basic.GeoAssoc geoId="CHN_45" toGeoId="CHN_45_5" geoAssocTypeEnumId="GAT_REGIONS"/>
    <moqui.basic.GeoAssoc geoId="CHN_45" toGeoId="CHN_45_6" geoAssocTypeEnumId="GAT_REGIONS"/>
    <moqui.basic.GeoAssoc geoId="CHN_45" toGeoId="CHN_45_7" geoAssocTypeEnumId="GAT_REGIONS"/>
    <moqui.basic.GeoAssoc geoId="CHN_45" toGeoId="CHN_45_8" geoAssocTypeEnumId="GAT_REGIONS"/>
    <moqui.basic.GeoAssoc geoId="CHN_45" toGeoId="CHN_45_9" geoAssocTypeEnumId="GAT_REGIONS"/>
    <moqui.basic.GeoAssoc geoId="CHN_45" toGeoId="CHN_45_10" geoAssocTypeEnumId="GAT_REGIONS"/>
    <moqui.basic.GeoAssoc geoId="CHN_45" toGeoId="CHN_45_11" geoAssocTypeEnumId="GAT_REGIONS"/>
    <moqui.basic.GeoAssoc geoId="CHN_45" toGeoId="CHN_45_12" geoAssocTypeEnumId="GAT_REGIONS"/>
    <moqui.basic.GeoAssoc geoId="CHN_45" toGeoId="CHN_45_13" geoAssocTypeEnumId="GAT_REGIONS"/>
    <moqui.basic.GeoAssoc geoId="CHN_45" toGeoId="CHN_45_14" geoAssocTypeEnumId="GAT_REGIONS"/>
    <moqui.basic.GeoAssoc geoId="CHN_53" toGeoId="CHN_53_1" geoAssocTypeEnumId="GAT_REGIONS"/>
    <moqui.basic.GeoAssoc geoId="CHN_53" toGeoId="CHN_53_2" geoAssocTypeEnumId="GAT_REGIONS"/>
    <moqui.basic.GeoAssoc geoId="CHN_53" toGeoId="CHN_53_3" geoAssocTypeEnumId="GAT_REGIONS"/>
    <moqui.basic.GeoAssoc geoId="CHN_53" toGeoId="CHN_53_4" geoAssocTypeEnumId="GAT_REGIONS"/>
    <moqui.basic.GeoAssoc geoId="CHN_53" toGeoId="CHN_53_5" geoAssocTypeEnumId="GAT_REGIONS"/>
    <moqui.basic.GeoAssoc geoId="CHN_53" toGeoId="CHN_53_6" geoAssocTypeEnumId="GAT_REGIONS"/>
    <moqui.basic.GeoAssoc geoId="CHN_53" toGeoId="CHN_53_7" geoAssocTypeEnumId="GAT_REGIONS"/>
    <moqui.basic.GeoAssoc geoId="CHN_53" toGeoId="CHN_53_8" geoAssocTypeEnumId="GAT_REGIONS"/>
    <moqui.basic.GeoAssoc geoId="CHN_53" toGeoId="CHN_53_9" geoAssocTypeEnumId="GAT_REGIONS"/>
    <moqui.basic.GeoAssoc geoId="CHN_53" toGeoId="CHN_53_10" geoAssocTypeEnumId="GAT_REGIONS"/>
    <moqui.basic.GeoAssoc geoId="CHN_53" toGeoId="CHN_53_11" geoAssocTypeEnumId="GAT_REGIONS"/>
    <moqui.basic.GeoAssoc geoId="CHN_53" toGeoId="CHN_53_12" geoAssocTypeEnumId="GAT_REGIONS"/>
    <moqui.basic.GeoAssoc geoId="CHN_53" toGeoId="CHN_53_13" geoAssocTypeEnumId="GAT_REGIONS"/>
    <moqui.basic.GeoAssoc geoId="CHN_53" toGeoId="CHN_53_14" geoAssocTypeEnumId="GAT_REGIONS"/>
    <moqui.basic.GeoAssoc geoId="CHN_53" toGeoId="CHN_53_15" geoAssocTypeEnumId="GAT_REGIONS"/>
    <moqui.basic.GeoAssoc geoId="CHN_53" toGeoId="CHN_53_16" geoAssocTypeEnumId="GAT_REGIONS"/>
    <moqui.basic.GeoAssoc geoId="CHN_52" toGeoId="CHN_52_1" geoAssocTypeEnumId="GAT_REGIONS"/>
    <moqui.basic.GeoAssoc geoId="CHN_52" toGeoId="CHN_52_2" geoAssocTypeEnumId="GAT_REGIONS"/>
    <moqui.basic.GeoAssoc geoId="CHN_52" toGeoId="CHN_52_3" geoAssocTypeEnumId="GAT_REGIONS"/>
    <moqui.basic.GeoAssoc geoId="CHN_52" toGeoId="CHN_52_4" geoAssocTypeEnumId="GAT_REGIONS"/>
    <moqui.basic.GeoAssoc geoId="CHN_52" toGeoId="CHN_52_5" geoAssocTypeEnumId="GAT_REGIONS"/>
    <moqui.basic.GeoAssoc geoId="CHN_52" toGeoId="CHN_52_6" geoAssocTypeEnumId="GAT_REGIONS"/>
    <moqui.basic.GeoAssoc geoId="CHN_52" toGeoId="CHN_52_7" geoAssocTypeEnumId="GAT_REGIONS"/>
    <moqui.basic.GeoAssoc geoId="CHN_52" toGeoId="CHN_52_8" geoAssocTypeEnumId="GAT_REGIONS"/>
    <moqui.basic.GeoAssoc geoId="CHN_52" toGeoId="CHN_52_9" geoAssocTypeEnumId="GAT_REGIONS"/>
    <moqui.basic.GeoAssoc geoId="CHN_51" toGeoId="CHN_51_1" geoAssocTypeEnumId="GAT_REGIONS"/>
    <moqui.basic.GeoAssoc geoId="CHN_51" toGeoId="CHN_51_2" geoAssocTypeEnumId="GAT_REGIONS"/>
    <moqui.basic.GeoAssoc geoId="CHN_51" toGeoId="CHN_51_3" geoAssocTypeEnumId="GAT_REGIONS"/>
    <moqui.basic.GeoAssoc geoId="CHN_51" toGeoId="CHN_51_4" geoAssocTypeEnumId="GAT_REGIONS"/>
    <moqui.basic.GeoAssoc geoId="CHN_51" toGeoId="CHN_51_5" geoAssocTypeEnumId="GAT_REGIONS"/>
    <moqui.basic.GeoAssoc geoId="CHN_51" toGeoId="CHN_51_6" geoAssocTypeEnumId="GAT_REGIONS"/>
    <moqui.basic.GeoAssoc geoId="CHN_51" toGeoId="CHN_51_7" geoAssocTypeEnumId="GAT_REGIONS"/>
    <moqui.basic.GeoAssoc geoId="CHN_51" toGeoId="CHN_51_8" geoAssocTypeEnumId="GAT_REGIONS"/>
    <moqui.basic.GeoAssoc geoId="CHN_51" toGeoId="CHN_51_9" geoAssocTypeEnumId="GAT_REGIONS"/>
    <moqui.basic.GeoAssoc geoId="CHN_51" toGeoId="CHN_51_10" geoAssocTypeEnumId="GAT_REGIONS"/>
    <moqui.basic.GeoAssoc geoId="CHN_51" toGeoId="CHN_51_11" geoAssocTypeEnumId="GAT_REGIONS"/>
    <moqui.basic.GeoAssoc geoId="CHN_51" toGeoId="CHN_51_12" geoAssocTypeEnumId="GAT_REGIONS"/>
    <moqui.basic.GeoAssoc geoId="CHN_51" toGeoId="CHN_51_13" geoAssocTypeEnumId="GAT_REGIONS"/>
    <moqui.basic.GeoAssoc geoId="CHN_51" toGeoId="CHN_51_14" geoAssocTypeEnumId="GAT_REGIONS"/>
    <moqui.basic.GeoAssoc geoId="CHN_51" toGeoId="CHN_51_15" geoAssocTypeEnumId="GAT_REGIONS"/>
    <moqui.basic.GeoAssoc geoId="CHN_51" toGeoId="CHN_51_16" geoAssocTypeEnumId="GAT_REGIONS"/>
    <moqui.basic.GeoAssoc geoId="CHN_51" toGeoId="CHN_51_17" geoAssocTypeEnumId="GAT_REGIONS"/>
    <moqui.basic.GeoAssoc geoId="CHN_51" toGeoId="CHN_51_18" geoAssocTypeEnumId="GAT_REGIONS"/>
    <moqui.basic.GeoAssoc geoId="CHN_51" toGeoId="CHN_51_19" geoAssocTypeEnumId="GAT_REGIONS"/>
    <moqui.basic.GeoAssoc geoId="CHN_51" toGeoId="CHN_51_20" geoAssocTypeEnumId="GAT_REGIONS"/>
    <moqui.basic.GeoAssoc geoId="CHN_51" toGeoId="CHN_51_21" geoAssocTypeEnumId="GAT_REGIONS"/>
    <moqui.basic.GeoAssoc geoId="CHN_15" toGeoId="CHN_15_1" geoAssocTypeEnumId="GAT_REGIONS"/>
    <moqui.basic.GeoAssoc geoId="CHN_15" toGeoId="CHN_15_2" geoAssocTypeEnumId="GAT_REGIONS"/>
    <moqui.basic.GeoAssoc geoId="CHN_15" toGeoId="CHN_15_3" geoAssocTypeEnumId="GAT_REGIONS"/>
    <moqui.basic.GeoAssoc geoId="CHN_15" toGeoId="CHN_15_4" geoAssocTypeEnumId="GAT_REGIONS"/>
    <moqui.basic.GeoAssoc geoId="CHN_15" toGeoId="CHN_15_5" geoAssocTypeEnumId="GAT_REGIONS"/>
    <moqui.basic.GeoAssoc geoId="CHN_15" toGeoId="CHN_15_6" geoAssocTypeEnumId="GAT_REGIONS"/>
    <moqui.basic.GeoAssoc geoId="CHN_15" toGeoId="CHN_15_7" geoAssocTypeEnumId="GAT_REGIONS"/>
    <moqui.basic.GeoAssoc geoId="CHN_15" toGeoId="CHN_15_8" geoAssocTypeEnumId="GAT_REGIONS"/>
    <moqui.basic.GeoAssoc geoId="CHN_15" toGeoId="CHN_15_9" geoAssocTypeEnumId="GAT_REGIONS"/>
    <moqui.basic.GeoAssoc geoId="CHN_15" toGeoId="CHN_15_10" geoAssocTypeEnumId="GAT_REGIONS"/>
    <moqui.basic.GeoAssoc geoId="CHN_15" toGeoId="CHN_15_11" geoAssocTypeEnumId="GAT_REGIONS"/>
    <moqui.basic.GeoAssoc geoId="CHN_15" toGeoId="CHN_15_12" geoAssocTypeEnumId="GAT_REGIONS"/>
    <moqui.basic.GeoAssoc geoId="CHN_64" toGeoId="CHN_64_1" geoAssocTypeEnumId="GAT_REGIONS"/>
    <moqui.basic.GeoAssoc geoId="CHN_64" toGeoId="CHN_64_2" geoAssocTypeEnumId="GAT_REGIONS"/>
    <moqui.basic.GeoAssoc geoId="CHN_64" toGeoId="CHN_64_3" geoAssocTypeEnumId="GAT_REGIONS"/>
    <moqui.basic.GeoAssoc geoId="CHN_64" toGeoId="CHN_64_4" geoAssocTypeEnumId="GAT_REGIONS"/>
    <moqui.basic.GeoAssoc geoId="CHN_64" toGeoId="CHN_64_5" geoAssocTypeEnumId="GAT_REGIONS"/>
    <moqui.basic.GeoAssoc geoId="CHN_62" toGeoId="CHN_62_1" geoAssocTypeEnumId="GAT_REGIONS"/>
    <moqui.basic.GeoAssoc geoId="CHN_62" toGeoId="CHN_62_2" geoAssocTypeEnumId="GAT_REGIONS"/>
    <moqui.basic.GeoAssoc geoId="CHN_62" toGeoId="CHN_62_3" geoAssocTypeEnumId="GAT_REGIONS"/>
    <moqui.basic.GeoAssoc geoId="CHN_62" toGeoId="CHN_62_4" geoAssocTypeEnumId="GAT_REGIONS"/>
    <moqui.basic.GeoAssoc geoId="CHN_62" toGeoId="CHN_62_5" geoAssocTypeEnumId="GAT_REGIONS"/>
    <moqui.basic.GeoAssoc geoId="CHN_62" toGeoId="CHN_62_6" geoAssocTypeEnumId="GAT_REGIONS"/>
    <moqui.basic.GeoAssoc geoId="CHN_62" toGeoId="CHN_62_7" geoAssocTypeEnumId="GAT_REGIONS"/>
    <moqui.basic.GeoAssoc geoId="CHN_62" toGeoId="CHN_62_8" geoAssocTypeEnumId="GAT_REGIONS"/>
    <moqui.basic.GeoAssoc geoId="CHN_62" toGeoId="CHN_62_9" geoAssocTypeEnumId="GAT_REGIONS"/>
    <moqui.basic.GeoAssoc geoId="CHN_62" toGeoId="CHN_62_10" geoAssocTypeEnumId="GAT_REGIONS"/>
    <moqui.basic.GeoAssoc geoId="CHN_62" toGeoId="CHN_62_11" geoAssocTypeEnumId="GAT_REGIONS"/>
    <moqui.basic.GeoAssoc geoId="CHN_62" toGeoId="CHN_62_12" geoAssocTypeEnumId="GAT_REGIONS"/>
    <moqui.basic.GeoAssoc geoId="CHN_62" toGeoId="CHN_62_13" geoAssocTypeEnumId="GAT_REGIONS"/>
    <moqui.basic.GeoAssoc geoId="CHN_62" toGeoId="CHN_62_14" geoAssocTypeEnumId="GAT_REGIONS"/>
    <moqui.basic.GeoAssoc geoId="CHN_63" toGeoId="CHN_63_1" geoAssocTypeEnumId="GAT_REGIONS"/>
    <moqui.basic.GeoAssoc geoId="CHN_63" toGeoId="CHN_63_2" geoAssocTypeEnumId="GAT_REGIONS"/>
    <moqui.basic.GeoAssoc geoId="CHN_63" toGeoId="CHN_63_3" geoAssocTypeEnumId="GAT_REGIONS"/>
    <moqui.basic.GeoAssoc geoId="CHN_63" toGeoId="CHN_63_4" geoAssocTypeEnumId="GAT_REGIONS"/>
    <moqui.basic.GeoAssoc geoId="CHN_63" toGeoId="CHN_63_5" geoAssocTypeEnumId="GAT_REGIONS"/>
    <moqui.basic.GeoAssoc geoId="CHN_63" toGeoId="CHN_63_6" geoAssocTypeEnumId="GAT_REGIONS"/>
    <moqui.basic.GeoAssoc geoId="CHN_63" toGeoId="CHN_63_7" geoAssocTypeEnumId="GAT_REGIONS"/>
    <moqui.basic.GeoAssoc geoId="CHN_63" toGeoId="CHN_63_8" geoAssocTypeEnumId="GAT_REGIONS"/>
    <moqui.basic.GeoAssoc geoId="CHN_54" toGeoId="CHN_54_1" geoAssocTypeEnumId="GAT_REGIONS"/>
    <moqui.basic.GeoAssoc geoId="CHN_54" toGeoId="CHN_54_2" geoAssocTypeEnumId="GAT_REGIONS"/>
    <moqui.basic.GeoAssoc geoId="CHN_54" toGeoId="CHN_54_3" geoAssocTypeEnumId="GAT_REGIONS"/>
    <moqui.basic.GeoAssoc geoId="CHN_54" toGeoId="CHN_54_4" geoAssocTypeEnumId="GAT_REGIONS"/>
    <moqui.basic.GeoAssoc geoId="CHN_54" toGeoId="CHN_54_5" geoAssocTypeEnumId="GAT_REGIONS"/>
    <moqui.basic.GeoAssoc geoId="CHN_54" toGeoId="CHN_54_6" geoAssocTypeEnumId="GAT_REGIONS"/>
    <moqui.basic.GeoAssoc geoId="CHN_54" toGeoId="CHN_54_7" geoAssocTypeEnumId="GAT_REGIONS"/>
    <moqui.basic.GeoAssoc geoId="CHN_65" toGeoId="CHN_65_1" geoAssocTypeEnumId="GAT_REGIONS"/>
    <moqui.basic.GeoAssoc geoId="CHN_65" toGeoId="CHN_65_2" geoAssocTypeEnumId="GAT_REGIONS"/>
    <moqui.basic.GeoAssoc geoId="CHN_65" toGeoId="CHN_65_3" geoAssocTypeEnumId="GAT_REGIONS"/>
    <moqui.basic.GeoAssoc geoId="CHN_65" toGeoId="CHN_65_4" geoAssocTypeEnumId="GAT_REGIONS"/>
    <moqui.basic.GeoAssoc geoId="CHN_65" toGeoId="CHN_65_5" geoAssocTypeEnumId="GAT_REGIONS"/>
    <moqui.basic.GeoAssoc geoId="CHN_65" toGeoId="CHN_65_6" geoAssocTypeEnumId="GAT_REGIONS"/>
    <moqui.basic.GeoAssoc geoId="CHN_65" toGeoId="CHN_65_7" geoAssocTypeEnumId="GAT_REGIONS"/>
    <moqui.basic.GeoAssoc geoId="CHN_65" toGeoId="CHN_65_8" geoAssocTypeEnumId="GAT_REGIONS"/>
    <moqui.basic.GeoAssoc geoId="CHN_65" toGeoId="CHN_65_9" geoAssocTypeEnumId="GAT_REGIONS"/>
    <moqui.basic.GeoAssoc geoId="CHN_65" toGeoId="CHN_65_10" geoAssocTypeEnumId="GAT_REGIONS"/>
    <moqui.basic.GeoAssoc geoId="CHN_65" toGeoId="CHN_65_11" geoAssocTypeEnumId="GAT_REGIONS"/>
    <moqui.basic.GeoAssoc geoId="CHN_65" toGeoId="CHN_65_12" geoAssocTypeEnumId="GAT_REGIONS"/>
    <moqui.basic.GeoAssoc geoId="CHN_65" toGeoId="CHN_65_13" geoAssocTypeEnumId="GAT_REGIONS"/>
    <moqui.basic.GeoAssoc geoId="CHN_65" toGeoId="CHN_65_14" geoAssocTypeEnumId="GAT_REGIONS"/>
    <moqui.basic.GeoAssoc geoId="CHN_65" toGeoId="CHN_65_15" geoAssocTypeEnumId="GAT_REGIONS"/>
    <moqui.basic.GeoAssoc geoId="CHN_65" toGeoId="CHN_65_16" geoAssocTypeEnumId="GAT_REGIONS"/>
    <moqui.basic.GeoAssoc geoId="CHN_65" toGeoId="CHN_65_17" geoAssocTypeEnumId="GAT_REGIONS"/>
    <moqui.basic.GeoAssoc geoId="CHN_65" toGeoId="CHN_65_18" geoAssocTypeEnumId="GAT_REGIONS"/>
    <moqui.basic.GeoAssoc geoId="CHN_34" toGeoId="CHN_34_1" geoAssocTypeEnumId="GAT_REGIONS"/>
    <moqui.basic.GeoAssoc geoId="CHN_34" toGeoId="CHN_34_2" geoAssocTypeEnumId="GAT_REGIONS"/>
    <moqui.basic.GeoAssoc geoId="CHN_34" toGeoId="CHN_34_3" geoAssocTypeEnumId="GAT_REGIONS"/>
    <moqui.basic.GeoAssoc geoId="CHN_34" toGeoId="CHN_34_4" geoAssocTypeEnumId="GAT_REGIONS"/>
    <moqui.basic.GeoAssoc geoId="CHN_34" toGeoId="CHN_34_5" geoAssocTypeEnumId="GAT_REGIONS"/>
    <moqui.basic.GeoAssoc geoId="CHN_34" toGeoId="CHN_34_6" geoAssocTypeEnumId="GAT_REGIONS"/>
    <moqui.basic.GeoAssoc geoId="CHN_34" toGeoId="CHN_34_7" geoAssocTypeEnumId="GAT_REGIONS"/>
    <moqui.basic.GeoAssoc geoId="CHN_34" toGeoId="CHN_34_8" geoAssocTypeEnumId="GAT_REGIONS"/>
    <moqui.basic.GeoAssoc geoId="CHN_34" toGeoId="CHN_34_9" geoAssocTypeEnumId="GAT_REGIONS"/>
    <moqui.basic.GeoAssoc geoId="CHN_34" toGeoId="CHN_34_10" geoAssocTypeEnumId="GAT_REGIONS"/>
    <moqui.basic.GeoAssoc geoId="CHN_34" toGeoId="CHN_34_11" geoAssocTypeEnumId="GAT_REGIONS"/>
    <moqui.basic.GeoAssoc geoId="CHN_34" toGeoId="CHN_34_12" geoAssocTypeEnumId="GAT_REGIONS"/>
    <moqui.basic.GeoAssoc geoId="CHN_34" toGeoId="CHN_34_13" geoAssocTypeEnumId="GAT_REGIONS"/>
    <moqui.basic.GeoAssoc geoId="CHN_34" toGeoId="CHN_34_14" geoAssocTypeEnumId="GAT_REGIONS"/>
    <moqui.basic.GeoAssoc geoId="CHN_34" toGeoId="CHN_34_15" geoAssocTypeEnumId="GAT_REGIONS"/>
    <moqui.basic.GeoAssoc geoId="CHN_34" toGeoId="CHN_34_16" geoAssocTypeEnumId="GAT_REGIONS"/>
    <moqui.basic.GeoAssoc geoId="CHN_34" toGeoId="CHN_34_17" geoAssocTypeEnumId="GAT_REGIONS"/>
    <moqui.basic.GeoAssoc geoId="CHN_33" toGeoId="CHN_33_1" geoAssocTypeEnumId="GAT_REGIONS"/>
    <moqui.basic.GeoAssoc geoId="CHN_33" toGeoId="CHN_33_2" geoAssocTypeEnumId="GAT_REGIONS"/>
    <moqui.basic.GeoAssoc geoId="CHN_33" toGeoId="CHN_33_3" geoAssocTypeEnumId="GAT_REGIONS"/>
    <moqui.basic.GeoAssoc geoId="CHN_33" toGeoId="CHN_33_4" geoAssocTypeEnumId="GAT_REGIONS"/>
    <moqui.basic.GeoAssoc geoId="CHN_33" toGeoId="CHN_33_5" geoAssocTypeEnumId="GAT_REGIONS"/>
    <moqui.basic.GeoAssoc geoId="CHN_33" toGeoId="CHN_33_6" geoAssocTypeEnumId="GAT_REGIONS"/>
    <moqui.basic.GeoAssoc geoId="CHN_33" toGeoId="CHN_33_7" geoAssocTypeEnumId="GAT_REGIONS"/>
    <moqui.basic.GeoAssoc geoId="CHN_33" toGeoId="CHN_33_8" geoAssocTypeEnumId="GAT_REGIONS"/>
    <moqui.basic.GeoAssoc geoId="CHN_33" toGeoId="CHN_33_9" geoAssocTypeEnumId="GAT_REGIONS"/>
    <moqui.basic.GeoAssoc geoId="CHN_33" toGeoId="CHN_33_10" geoAssocTypeEnumId="GAT_REGIONS"/>
    <moqui.basic.GeoAssoc geoId="CHN_33" toGeoId="CHN_33_11" geoAssocTypeEnumId="GAT_REGIONS"/>
    <moqui.basic.GeoAssoc geoId="CHN_35" toGeoId="CHN_35_1" geoAssocTypeEnumId="GAT_REGIONS"/>
    <moqui.basic.GeoAssoc geoId="CHN_35" toGeoId="CHN_35_2" geoAssocTypeEnumId="GAT_REGIONS"/>
    <moqui.basic.GeoAssoc geoId="CHN_35" toGeoId="CHN_35_3" geoAssocTypeEnumId="GAT_REGIONS"/>
    <moqui.basic.GeoAssoc geoId="CHN_35" toGeoId="CHN_35_4" geoAssocTypeEnumId="GAT_REGIONS"/>
    <moqui.basic.GeoAssoc geoId="CHN_35" toGeoId="CHN_35_5" geoAssocTypeEnumId="GAT_REGIONS"/>
    <moqui.basic.GeoAssoc geoId="CHN_35" toGeoId="CHN_35_6" geoAssocTypeEnumId="GAT_REGIONS"/>
    <moqui.basic.GeoAssoc geoId="CHN_35" toGeoId="CHN_35_7" geoAssocTypeEnumId="GAT_REGIONS"/>
    <moqui.basic.GeoAssoc geoId="CHN_35" toGeoId="CHN_35_8" geoAssocTypeEnumId="GAT_REGIONS"/>
    <moqui.basic.GeoAssoc geoId="CHN_35" toGeoId="CHN_35_9" geoAssocTypeEnumId="GAT_REGIONS"/>

</entity-facade-xml>